Workbook

Sheet Cover
B3: ETERNAL LIMITED
B4: (formerly Zomato Limited)
B5: DCF Valuation Report — Three-Case Scenario Framework
B7: NSE: ETERNAL | E7: ="Valuation Date: "&TEXT(TODAY(),"d-mmm-yyyy") -> Valuation Date: 6-May-2026
B8: ="Decision rule: BUY if weighted upside ≥ "&TEXT(I12,"0.0%")&" • HOLD if 0% to "&TEXT(I12,"0.0%")&" • REDUCE if "&TEXT(I14,"0.0%")&" to 0% • SELL if < "&TEXT(I14,"0.0%") -> Decision rule: BUY if weighted upside ≥ 15.0% • HOLD if 0% to 15.0% • REDUCE if -15.0% to 0% • SELL if < -15.0%
B10: INVESTMENT RECOMMENDATION | H10: Decision Thresholds
B11: CURRENT PRICE | C11: IMPLIED PRICE (Active Case) | D11: PROB-WEIGHTED PRICE | E11: RECOMMENDATION | H11: Metric | I11: Threshold
B12: =Assumptions!F7 -> 251 | C12: =DCF!F54 -> 287.17054 | D12: =Summary!C43 -> 141.82559 | E12: =IF(Summary!F43>=I12,"BUY",IF(Summary!F43>=I13,"HOLD",IF(Summary!F43>=I14,"REDUCE","SELL"))) -> SELL | H12: BUY threshold | I12: 0.15
B13: NSE close (input) | C13: ="vs current: "&TEXT(DCF!F56,"+0.0%;-0.0%") -> vs current: +14.4% | D13: ="vs current: "&TEXT(Summary!F43,"+0.0%;-0.0%") -> vs current: -43.5% | E13: ="Weighted upside: "&TEXT(Summary!F43,"+0.0%;-0.0%") -> Weighted upside: -43.5% | H13: HOLD threshold | I13: 0
H14: SELL threshold | I14: -0.15
B16: COMPANY SNAPSHOT
B17: Company Name | C17: Eternal Limited (formerly Zomato Limited) | D17: Headquarters | E17: Gurugram, Haryana, India
B18: Listing | C18: NSE & BSE | D18: Ticker | E18: ETERNAL (NSE.ETERNAL)
B19: Founded | C19: 2008 | D19: Founders | E19: Deepinder Goyal & Pankaj Chaddah
B20: Industry | C20: Internet — Food, Quick Commerce & Lifestyle | D20: Sector | E20: Consumer Internet
B21: Rebrand Date | C21: 9 April 2025 (Zomato → Eternal) | D21: Currency | E21: INR (₹), figures in crores
B22: Reporting Period | C22: FY22 — FY25 (historicals); FY26E — FY35E (forecast) | D22: Status | E22: Listed Public Limited
B24: BUSINESS SEGMENTS
B25: Segment | C25: Description | D25: Latest NOV (Q4 FY26) | E25: Strategic Status
B26: Food Delivery | C26: Restaurant marketplace & delivery (Zomato app); core consumer business with 25.4M MTC | D26: ₹9,760 Cr (+19% YoY) | E26: Profitable; ~5.5% adj. EBITDA margin
B27: Quick Commerce (Blinkit) | C27: Instant grocery via 2,243+ dark stores; fastest-growing vertical, transitioning to 1P inventory model | D27: ₹14,390 Cr (+121% YoY) | E27: Adj. EBITDA-positive (Q3 FY26)
B28: Hyperpure (B2B) | C28: B2B fresh-ingredient supply chain to restaurants & food businesses; strategic ecosystem moat | D28: ₹980 Cr | E28: Adj. EBITDA-positive (Q3 FY26)
B29: Going Out | C29: Events, ticketing, experiences, District Pass loyalty product; offline lifestyle play | D29: +46% YoY (NOV) | E29: Investment phase; loss ~₹81 Cr
B31: VALUATION APPROACH
B32: Methodology | C32: 10-year FCFF DCF with Gordon-growth terminal value
B33: Forecast Horizon | C33: FY26E — FY35E explicit forecast period; perpetuity thereafter
B34: Cost of Capital | C34: WACC build via CAPM (Rf + β × ERP); blended with after-tax cost of debt at target capital structure
B35: Scenario Framework | C35: Base / Optimistic / Pessimistic — each with case-specific WACC, segment growth, margins, & terminal growth
B37: SCENARIO OUTPUTS — IMPLIED EQUITY VALUE PER SHARE
B38: Scenario | C38: WACC | D38: Implied / share | E38: Upside / (Downside)
B39: Base Case | C39: =Assumptions!T24 -> 0.13021171 | D39: =Scenarios!D52 -> 87.613016 | E39: =Scenarios!D54 -> -0.65094416
B40: Optimistic Case | C40: =Assumptions!U24 -> 0.12017267 | D40: =Scenarios!D103 -> 287.17054 | E40: =Scenarios!D105 -> 0.14410573
B41: Pessimistic Case | C41: =Assumptions!V24 -> 0.14359709 | D41: =Scenarios!D154 -> 25.0828 | E41: =Scenarios!D156 -> -0.90006853
B43: HOW TO NAVIGATE THIS MODEL
B44: 1. Summary | C44: Executive summary with active scenario card, full 3-case comparison & probability-weighted view
B45: 2. Assumptions | C45: All model inputs — WACC build, terminal value, segment drivers; toggle Summary!F5 to switch scenario
B46: 3. Scenarios | C46: Three parallel mini-DCFs (Base / Optimistic / Pessimistic) running simultaneously
B47: 4. DCF | C47: Main DCF tied to active scenario; FCFF derivation, discounted cash flows, EV bridge
B48: 5. Sensitivity | C48: 2D sensitivity tables — WACC × terminal growth and WACC × terminal margin
B49: 6. Historicals | C49: Balance Sheet, P&L, Cash Flow, Equity statements (FY22-FY25) extracted from annual reports
B51: Source: Eternal Ltd. Annual Reports FY22-FY25; NSE/BSE filings; brokerage research; management Q4 FY26 commentary
B52: Prepared as part of independent academic / analytical exercise — Valuation date: 5-May-2026
B53: Disclaimer: This valuation is for illustrative & educational purposes only. It does not constitute investment advice, recommendation, or solicitation. All figures are model outputs subject to assumptions; actual results may differ materially.

Sheet Summary
A1: Eternal Limited (formerly Zomato Limited) — DCF Valuation Summary
A2: Three-case scenario DCF — base / optimistic / pessimistic. All values in INR crores unless stated. Valuation date: 5-May-2026.
A4: ACTIVE SCENARIO (live link to toggle)
A5: Active case | B5: =Assumptions!T7 -> Optimistic Case | D5: Toggle (1=Base / 2=Opt / 3=Pess): | F5: 1
A6: Active implied / share | B6: =DCF!F54 -> 287.17054 | D6: Active upside / (downside) | F6: =DCF!F56 -> 0.14410573
A7: To switch scenario, change F5 above (1=Base / 2=Optimistic / 3=Pessimistic). DCF, Sensitivity, Assumptions, and Summary auto-recompute.
A8: SCENARIO COMPARISON
A9: Metric | B9: Unit | C9: Base | D9: Optimistic | E9: Pessimistic | F9: Opt – Pess range
A10: Cost of capital & terminal
A11: WACC | B11: % | C11: =Assumptions!T24 -> 0.13021171 | D11: =Assumptions!U24 -> 0.12017267 | E11: =Assumptions!V24 -> 0.14359709 | F11: =D11-E11 -> -0.023424424
A12: Beta (levered) | B12: x | C12: =Assumptions!T17 -> 0.9 | D12: =Assumptions!U17 -> 0.75 | E12: =Assumptions!V17 -> 1.1 | F12: =D12-E12 -> -0.35
A13: Terminal growth (perpetual) | B13: % | C13: =Assumptions!T28 -> 0.05 | D13: =Assumptions!U28 -> 0.06 | E13: =Assumptions!V28 -> 0.04 | F13: =D13-E13 -> 0.02
A15: Revenue trajectory
A16: FY26E Total Revenue | B16: ₹ Cr | C16: =Scenarios!D14 -> 32235.8 | D16: =Scenarios!D65 -> 34449.2 | E16: =Scenarios!D116 -> 29713.32 | F16: =D16-E16 -> 4735.88
A17: FY30E Total Revenue | B17: ₹ Cr | C17: =Scenarios!H14 -> 111899.78 | D17: =Scenarios!H65 -> 158585.8 | E17: =Scenarios!H116 -> 76077.748 | F17: =D17-E17 -> 82508.054
A18: FY35E Total Revenue | B18: ₹ Cr | C18: =Scenarios!M14 -> 226238.24 | D18: =Scenarios!M65 -> 413523.93 | E18: =Scenarios!M116 -> 119326.63 | F18: =D18-E18 -> 294197.3
A19: Revenue CAGR FY25–FY35 | B19: % | C19: =(Scenarios!M14/Scenarios!C14)^(1/10)-1 -> 0.27300208 | D19: =(Scenarios!M65/Scenarios!C65)^(1/10)-1 -> 0.35214285 | E19: =(Scenarios!M116/Scenarios!C116)^(1/10)-1 -> 0.19411527 | F19: =D19-E19 -> 0.15802759
A21: Steady-state profitability (FY35E)
A22: Adj. EBITDA margin | B22: % | C22: =Scenarios!M24 -> 0.13366474 | D22: =Scenarios!M75 -> 0.16223003 | E22: =Scenarios!M126 -> 0.10399943 | F22: =D22-E22 -> 0.058230604
A23: EBIT margin | B23: % | C23: =Scenarios!M30 -> 0.083664739 | D23: =Scenarios!M81 -> 0.11623003 | E23: =Scenarios!M132 -> 0.045999427 | F23: =D23-E23 -> 0.070230604
A24: FCFF margin | B24: % | C24: =Scenarios!M37 -> 0.058140812 | D24: =Scenarios!M88 -> 0.085309833 | E24: =Scenarios!M139 -> 0.031138673 | F24: =D24-E24 -> 0.05417116
A25: FY35E FCFF | B25: ₹ Cr | C25: =Scenarios!M36 -> 13153.675 | D25: =Scenarios!M87 -> 35277.657 | E25: =Scenarios!M138 -> 3715.6729 | F25: =D25-E25 -> 31561.984
A27: Valuation bridge
A28: Sum of PV of explicit FCFF | B28: ₹ Cr | C28: =Scenarios!D43 -> 17973.636 | D28: =Scenarios!D94 -> 58699.654 | E28: =Scenarios!D145 -> -644.45088 | F28: =D28-E28 -> 59344.105
A29: PV of Terminal Value | B29: ₹ Cr | C29: =Scenarios!D46 -> 50629.149 | D29: =Scenarios!D97 -> 199782.11 | E29: =Scenarios!D148 -> 9749.7352 | F29: =D29-E29 -> 190032.38
A30: Enterprise Value | B30: ₹ Cr | C30: =Scenarios!D47 -> 68602.785 | D30: =Scenarios!D98 -> 258481.77 | E30: =Scenarios!D149 -> 9105.2844 | F30: =D30-E30 -> 249376.48
A31: Less: Total debt | B31: ₹ Cr | C31: =Scenarios!D48 -> -2045 | D31: =Scenarios!D99 -> -2045 | E31: =Scenarios!D150 -> -2045 | F31: =D31-E31 -> 0
A32: Plus: Cash & investments | B32: ₹ Cr | C32: =Scenarios!D49 -> 16806 | D32: =Scenarios!D100 -> 16806 | E32: =Scenarios!D151 -> 16806 | F32: =D32-E32 -> 0
A33: Equity Value | B33: ₹ Cr | C33: =Scenarios!D50 -> 83363.785 | D33: =Scenarios!D101 -> 273242.77 | E33: =Scenarios!D152 -> 23866.284 | F33: =D33-E33 -> 249376.48
A35: Per share
A36: Shares outstanding | B36: cr | C36: =Scenarios!D51 -> 951.5 | D36: =Scenarios!D102 -> 951.5 | E36: =Scenarios!D153 -> 951.5 | F36: =D36-E36 -> 0
A37: Implied per share value | B37: ₹ | C37: =Scenarios!D52 -> 87.613016 | D37: =Scenarios!D103 -> 287.17054 | E37: =Scenarios!D154 -> 25.0828 | F37: =D37-E37 -> 262.08774
A38: Current share price | B38: ₹ | C38: =Scenarios!D53 -> 251 | D38: =Scenarios!D104 -> 251 | E38: =Scenarios!D155 -> 251 | F38: =D38-E38 -> 0
A39: Implied upside / (downside) | B39: % | C39: =Scenarios!D54 -> -0.65094416 | D39: =Scenarios!D105 -> 0.14410573 | E39: =Scenarios!D156 -> -0.90006853 | F39: =D39-E39 -> 1.0441743
A41: INVESTMENT VIEW
A42: Probability-weighted equity value (40% Base / 35% Opt / 25% Pess) | B42: ₹ Cr | C42: =B45*Scenarios!D50+D45*Scenarios!D101+F45*Scenarios!D152 -> 134947.05
A43: Probability-weighted implied per share | B43: ₹ | C43: =C42/Assumptions!F8 -> 141.82559 | D43: vs current price | E43: =Assumptions!F7 -> 251 | F43: =C43/E43-1 -> -0.43495779
A44: Probability weights are illustrative and editable here:
A45: Base weight | B45: 0.4 | C45: Optimistic weight | D45: 0.35 | E45: Pessimistic weight | F45: 0.25
A46: Sum check (must = 100%) | B46: =B45+D45+F45 -> 1 | C46: =IF(ABS(B46-1)<0.001,"OK","Check weights") -> OK
A48: KEY TAKEAWAYS
A49: 1. Valuation is highly sensitive to long-run profitability and segment growth — the optimistic / pessimistic spread is wide.
A50: 2. Quick Commerce (Blinkit) economics are the single largest swing factor: terminal margin assumed 15% (Base) vs 19% (Opt) vs 11% (Pess).
A51: 3. Base case implies meaningful downside vs market, suggesting consensus prices in faster scaling and higher steady-state margins than the Base assumptions.
A52: 4. Cross-check: review Sensitivity sheet for WACC × terminal-g grid and Scenarios sheet for full P&L bridges.

Sheet Assumptions
A1: Eternal Limited (formerly Zomato Limited) — DCF Valuation Assumptions
A2: Valuation date: 5 May 2026. All financials in INR crores unless stated. Forecast period: FY26E–FY35E + Terminal. | S2: =T7 -> Optimistic Case
A4: Particulars | B4: Unit | C4: FY22A | D4: FY23A | E4: FY24A | F4: FY25A | G4: FY26E | H4: FY27E | I4: FY28E | J4: FY29E | K4: FY30E | L4: FY31E | M4: FY32E | N4: FY33E | O4: FY34E | P4: FY35E | Q4: Terminal | S4: Scenario Control
A5: MARKET & CAPITAL STRUCTURE
A6: Valuation date | F6: 46147 | S6: Active scenario: | T6: 2
A7: Current share price (NSE: ETERNAL) | B7: ₹ | F7: 251 | S7: Case name: | T7: =CHOOSE(T6,"Base Case","Optimistic Case","Pessimistic Case") -> Optimistic Case
A8: Shares outstanding | B8: cr | F8: 951.5
A9: Market capitalisation | B9: ₹ Cr | F9: =F7*F8 -> 238826.5
A10: Total debt (lease liab. + borrowings) | B10: ₹ Cr | F10: ='Balance Sheet'!F39+'Balance Sheet'!F47+'Balance Sheet'!F38+'Balance Sheet'!F46 -> 2045
A11: Cash, bank & investments | B11: ₹ Cr | F11: ='Balance Sheet'!F13+'Balance Sheet'!F20+'Balance Sheet'!F22+'Balance Sheet'!F23 -> 16806
A12: Total capital (Equity + Debt) | B12: ₹ Cr | F12: =F9+F10 -> 240871.5
A14: WACC BUILD
A15: Risk-free rate (10Y India G-Sec) | B15: % | F15: 0.07
A16: Equity Risk Premium (India) | B16: % | F16: 0.0675
A17: Beta (levered, forward-looking) | B17: x | F17: =CHOOSE($T$6,T17,U17,V17) -> 0.75 | S17: Beta — case input | T17: 0.9 | U17: 0.75 | V17: 1.1
A18: Cost of equity (CAPM) | B18: % | F18: =F15+F17*F16 -> 0.120625 | S18: Cost of equity — case | T18: =$F$15+T17*$F$16 -> 0.13075 | U18: =$F$15+U17*$F$16 -> 0.120625 | V18: =$F$15+V17*$F$16 -> 0.14425
A19: Pre-tax cost of debt | B19: % | F19: 0.09
A20: Statutory tax rate (Section 115BAA) | B20: % | F20: 0.2517
A21: After-tax cost of debt | B21: % | F21: =F19*(1-F20) -> 0.067347
A22: Weight of equity (E/V) | B22: % | F22: =F9/F12 -> 0.99151
A23: Weight of debt (D/V) | B23: % | F23: =F10/F12 -> 0.008490004
A24: WACC | B24: % | F24: =F22*F18+F23*F21 -> 0.12017267 | S24: WACC — case | T24: =$F$22*T18+$F$23*$F$21 -> 0.13021171 | U24: =$F$22*U18+$F$23*$F$21 -> 0.12017267 | V24: =$F$22*V18+$F$23*$F$21 -> 0.14359709
A26: TERMINAL ASSUMPTIONS
A27: Forecast horizon | B27: yrs | F27: 10
A28: Terminal growth rate (perpetual) | B28: % | F28: =CHOOSE($T$6,T28,U28,V28) -> 0.06 | S28: Terminal g — case input | T28: 0.05 | U28: 0.06 | V28: 0.04
A29: Terminal effective tax rate | B29: % | F29: 0.2517
A32: Food Delivery | B32: % | G32: =CHOOSE($T$6,G56,G57,G58) -> 0.3 | H32: =CHOOSE($T$6,H56,H57,H58) -> 0.27 | I32: =CHOOSE($T$6,I56,I57,I58) -> 0.24 | J32: =CHOOSE($T$6,J56,J57,J58) -> 0.22 | K32: =CHOOSE($T$6,K56,K57,K58) -> 0.2 | L32: =CHOOSE($T$6,L56,L57,L58) -> 0.18 | M32: =CHOOSE($T$6,M56,M57,M58) -> 0.16 | N32: =CHOOSE($T$6,N56,N57,N58) -> 0.14 | ... Q32: =CHOOSE($T$6,Q56,Q57,Q58) -> 0.06
A33: Hyperpure (B2B supplies) | B33: % | G33: =CHOOSE($T$6,G59,G60,G61) -> 0.75 | H33: =CHOOSE($T$6,H59,H60,H61) -> 0.6 | I33: =CHOOSE($T$6,I59,I60,I61) -> 0.48 | J33: =CHOOSE($T$6,J59,J60,J61) -> 0.4 | K33: =CHOOSE($T$6,K59,K60,K61) -> 0.35 | L33: =CHOOSE($T$6,L59,L60,L61) -> 0.3 | M33: =CHOOSE($T$6,M59,M60,M61) -> 0.25 | N33: =CHOOSE($T$6,N59,N60,N61) -> 0.22 | ... Q33: =CHOOSE($T$6,Q59,Q60,Q61) -> 0.06
A34: Quick Commerce (Blinkit) | B34: % | G34: =CHOOSE($T$6,G62,G63,G64) -> 1.2 | H34: =CHOOSE($T$6,H62,H63,H64) -> 0.9 | I34: =CHOOSE($T$6,I62,I63,I64) -> 0.65 | J34: =CHOOSE($T$6,J62,J63,J64) -> 0.5 | K34: =CHOOSE($T$6,K62,K63,K64) -> 0.4 | L34: =CHOOSE($T$6,L62,L63,L64) -> 0.35 | M34: =CHOOSE($T$6,M62,M63,M64) -> 0.28 | N34: =CHOOSE($T$6,N62,N63,N64) -> 0.22 | ... Q34: =CHOOSE($T$6,Q62,Q63,Q64) -> 0.06
A35: Going Out | B35: % | G35: =CHOOSE($T$6,G65,G66,G67) -> 1.2 | H35: =CHOOSE($T$6,H65,H66,H67) -> 0.85 | I35: =CHOOSE($T$6,I65,I66,I67) -> 0.65 | J35: =CHOOSE($T$6,J65,J66,J67) -> 0.5 | K35: =CHOOSE($T$6,K65,K66,K67) -> 0.4 | L35: =CHOOSE($T$6,L65,L66,L67) -> 0.3 | M35: =CHOOSE($T$6,M65,M66,M67) -> 0.22 | N35: =CHOOSE($T$6,N65,N66,N67) -> 0.18 | ... Q35: =CHOOSE($T$6,Q65,Q66,Q67) -> 0.06
A36: All other segments | B36: % | G36: =CHOOSE($T$6,G68,G69,G70) -> 0.15 | H36: =CHOOSE($T$6,H68,H69,H70) -> 0.15 | I36: =CHOOSE($T$6,I68,I69,I70) -> 0.15 | J36: =CHOOSE($T$6,J68,J69,J70) -> 0.12 | K36: =CHOOSE($T$6,K68,K69,K70) -> 0.1 | L36: =CHOOSE($T$6,L68,L69,L70) -> 0.08 | M36: =CHOOSE($T$6,M68,M69,M70) -> 0.08 | N36: =CHOOSE($T$6,N68,N69,N70) -> 0.08 | ... Q36: =CHOOSE($T$6,Q68,Q69,Q70) -> 0.06
A38: SEGMENT MARGIN — Segment Result % of Segment Revenue
A39: Food Delivery | B39: % | G39: =CHOOSE($T$6,G73,G74,G75) -> 0.23 | H39: =CHOOSE($T$6,H73,H74,H75) -> 0.24 | I39: =CHOOSE($T$6,I73,I74,I75) -> 0.25 | J39: =CHOOSE($T$6,J73,J74,J75) -> 0.26 | K39: =CHOOSE($T$6,K73,K74,K75) -> 0.27 | L39: =CHOOSE($T$6,L73,L74,L75) -> 0.28 | M39: =CHOOSE($T$6,M73,M74,M75) -> 0.28 | N39: =CHOOSE($T$6,N73,N74,N75) -> 0.28 | ... Q39: =CHOOSE($T$6,Q73,Q74,Q75) -> 0.28
A40: Hyperpure (B2B supplies) | B40: % | G40: =CHOOSE($T$6,G76,G77,G78) -> 0.02 | H40: =CHOOSE($T$6,H76,H77,H78) -> 0.03 | I40: =CHOOSE($T$6,I76,I77,I78) -> 0.04 | J40: =CHOOSE($T$6,J76,J77,J78) -> 0.05 | K40: =CHOOSE($T$6,K76,K77,K78) -> 0.06 | L40: =CHOOSE($T$6,L76,L77,L78) -> 0.07 | M40: =CHOOSE($T$6,M76,M77,M78) -> 0.07 | N40: =CHOOSE($T$6,N76,N77,N78) -> 0.07 | ... Q40: =CHOOSE($T$6,Q76,Q77,Q78) -> 0.07
A41: Quick Commerce (Blinkit) | B41: % | G41: =CHOOSE($T$6,G79,G80,G81) -> 0.03 | H41: =CHOOSE($T$6,H79,H80,H81) -> 0.07 | I41: =CHOOSE($T$6,I79,I80,I81) -> 0.11 | J41: =CHOOSE($T$6,J79,J80,J81) -> 0.14 | K41: =CHOOSE($T$6,K79,K80,K81) -> 0.16 | L41: =CHOOSE($T$6,L79,L80,L81) -> 0.17 | M41: =CHOOSE($T$6,M79,M80,M81) -> 0.18 | N41: =CHOOSE($T$6,N79,N80,N81) -> 0.19 | ... Q41: =CHOOSE($T$6,Q79,Q80,Q81) -> 0.19
A42: Going Out | B42: % | G42: =CHOOSE($T$6,G82,G83,G84) -> -0.03 | H42: =CHOOSE($T$6,H82,H83,H84) -> 0 | I42: =CHOOSE($T$6,I82,I83,I84) -> 0.04 | J42: =CHOOSE($T$6,J82,J83,J84) -> 0.08 | K42: =CHOOSE($T$6,K82,K83,K84) -> 0.12 | L42: =CHOOSE($T$6,L82,L83,L84) -> 0.15 | M42: =CHOOSE($T$6,M82,M83,M84) -> 0.17 | N42: =CHOOSE($T$6,N82,N83,N84) -> 0.18 | ... Q42: =CHOOSE($T$6,Q82,Q83,Q84) -> 0.19
A43: All other segments | B43: % | G43: =CHOOSE($T$6,G85,G86,G87) -> -0.2 | H43: =CHOOSE($T$6,H85,H86,H87) -> -0.1 | I43: =CHOOSE($T$6,I85,I86,I87) -> 0 | J43: =CHOOSE($T$6,J85,J86,J87) -> 0.05 | K43: =CHOOSE($T$6,K85,K86,K87) -> 0.08 | L43: =CHOOSE($T$6,L85,L86,L87) -> 0.08 | M43: =CHOOSE($T$6,M85,M86,M87) -> 0.08 | N43: =CHOOSE($T$6,N85,N86,N87) -> 0.08 | ... Q43: =CHOOSE($T$6,Q85,Q86,Q87) -> 0.08
A45: CONSOLIDATED RATIOS (% of Revenue unless stated)
A46: Share-based payment expense (SBP) | B46: % | G46: =CHOOSE($T$6,G90,G91,G92) -> 0.03 | H46: =CHOOSE($T$6,H90,H91,H92) -> 0.025 | I46: =CHOOSE($T$6,I90,I91,I92) -> 0.022 | J46: =CHOOSE($T$6,J90,J91,J92) -> 0.02 | K46: =CHOOSE($T$6,K90,K91,K92) -> 0.018 | L46: =CHOOSE($T$6,L90,L91,L92) -> 0.015 | M46: =CHOOSE($T$6,M90,M91,M92) -> 0.015 | N46: =CHOOSE($T$6,N90,N91,N92) -> 0.015 | ... Q46: =CHOOSE($T$6,Q90,Q91,Q92) -> 0.013
A47: Depreciation & amortisation (D&A) | B47: % | G47: =CHOOSE($T$6,G93,G94,G95) -> 0.04 | H47: =CHOOSE($T$6,H93,H94,H95) -> 0.038 | I47: =CHOOSE($T$6,I93,I94,I95) -> 0.036 | J47: =CHOOSE($T$6,J93,J94,J95) -> 0.035 | K47: =CHOOSE($T$6,K93,K94,K95) -> 0.034 | L47: =CHOOSE($T$6,L93,L94,L95) -> 0.033 | M47: =CHOOSE($T$6,M93,M94,M95) -> 0.033 | N47: =CHOOSE($T$6,N93,N94,N95) -> 0.033 | ... Q47: =CHOOSE($T$6,Q93,Q94,Q95) -> 0.033
A48: Capital expenditure (Capex) | B48: % | G48: =CHOOSE($T$6,G96,G97,G98) -> 0.05 | H48: =CHOOSE($T$6,H96,H97,H98) -> 0.045 | I48: =CHOOSE($T$6,I96,I97,I98) -> 0.04 | J48: =CHOOSE($T$6,J96,J97,J98) -> 0.035 | K48: =CHOOSE($T$6,K96,K97,K98) -> 0.033 | L48: =CHOOSE($T$6,L96,L97,L98) -> 0.03 | M48: =CHOOSE($T$6,M96,M97,M98) -> 0.03 | N48: =CHOOSE($T$6,N96,N97,N98) -> 0.03 | ... Q48: =CHOOSE($T$6,Q96,Q97,Q98) -> 0.03
A49: Change in NWC (% of Δ revenue) | B49: % | G49: =CHOOSE($T$6,G99,G100,G101) -> 0.07 | H49: =CHOOSE($T$6,H99,H100,H101) -> 0.07 | I49: =CHOOSE($T$6,I99,I100,I101) -> 0.06 | J49: =CHOOSE($T$6,J99,J100,J101) -> 0.06 | K49: =CHOOSE($T$6,K99,K100,K101) -> 0.05 | L49: =CHOOSE($T$6,L99,L100,L101) -> 0.05 | M49: =CHOOSE($T$6,M99,M100,M101) -> 0.05 | N49: =CHOOSE($T$6,N99,N100,N101) -> 0.04 | ... Q49: =CHOOSE($T$6,Q99,Q100,Q101) -> 0.04
A50: Effective tax rate | B50: % | G50: =CHOOSE($T$6,G102,G103,G104) -> 0 | H50: =CHOOSE($T$6,H102,H103,H104) -> 0 | I50: =CHOOSE($T$6,I102,I103,I104) -> 0.08 | J50: =CHOOSE($T$6,J102,J103,J104) -> 0.15 | K50: =CHOOSE($T$6,K102,K103,K104) -> 0.2 | L50: =CHOOSE($T$6,L102,L103,L104) -> 0.252 | M50: =CHOOSE($T$6,M102,M103,M104) -> 0.252 | N50: =CHOOSE($T$6,N102,N103,N104) -> 0.252 | ... Q50: =CHOOSE($T$6,Q102,Q103,Q104) -> 0.252
A51: Other income (treasury yield) | B51: % | G51: =CHOOSE($T$6,G105,G106,G107) -> 0.04 | H51: =CHOOSE($T$6,H105,H106,H107) -> 0.035 | I51: =CHOOSE($T$6,I105,I106,I107) -> 0.03 | J51: =CHOOSE($T$6,J105,J106,J107) -> 0.025 | K51: =CHOOSE($T$6,K105,K106,K107) -> 0.022 | L51: =CHOOSE($T$6,L105,L106,L107) -> 0.02 | M51: =CHOOSE($T$6,M105,M106,M107) -> 0.018 | N51: =CHOOSE($T$6,N105,N106,N107) -> 0.016 | ... Q51: =CHOOSE($T$6,Q105,Q106,Q107) -> 0.01
A53: SCENARIO INPUTS BY CASE — Edit values for each case; Active rows above pull via toggle
A54: To switch active scenario, change Summary!F5 (or Assumptions T6 — both linked) to 1=Base, 2=Optimistic, 3=Pessimistic
A55: Segment revenue growth (% YoY)
A56: Food Delivery — Base | B56: % | G56: 0.25 | H56: 0.22 | I56: 0.19 | J56: 0.17 | K56: 0.15 | L56: 0.13 | M56: 0.12 | N56: 0.11 | O56: 0.1 | P56: 0.09 | Q56: 0.05
A57: — Optimistic | B57: % | G57: 0.3 | H57: 0.27 | I57: 0.24 | J57: 0.22 | K57: 0.2 | L57: 0.18 | M57: 0.16 | N57: 0.14 | O57: 0.12 | P57: 0.1 | Q57: 0.06
A58: — Pessimistic | B58: % | G58: 0.2 | H58: 0.17 | I58: 0.14 | J58: 0.12 | K58: 0.1 | L58: 0.09 | M58: 0.08 | N58: 0.07 | O58: 0.06 | P58: 0.05 | Q58: 0.04
A59: Hyperpure (B2B supplies) — Base | B59: % | G59: 0.65 | H59: 0.5 | I59: 0.38 | J59: 0.3 | K59: 0.25 | L59: 0.22 | M59: 0.18 | N59: 0.15 | O59: 0.12 | P59: 0.1 | Q59: 0.05
A60: — Optimistic | B60: % | G60: 0.75 | H60: 0.6 | I60: 0.48 | J60: 0.4 | K60: 0.35 | L60: 0.3 | M60: 0.25 | N60: 0.22 | O60: 0.18 | P60: 0.15 | Q60: 0.06
A61: — Pessimistic | B61: % | G61: 0.5 | H61: 0.4 | I61: 0.28 | J61: 0.22 | K61: 0.18 | L61: 0.15 | M61: 0.12 | N61: 0.1 | O61: 0.08 | P61: 0.06 | Q61: 0.04
A62: Quick Commerce (Blinkit) — Base | B62: % | G62: 1 | H62: 0.75 | I62: 0.55 | J62: 0.4 | K62: 0.3 | L62: 0.25 | M62: 0.2 | N62: 0.16 | O62: 0.13 | P62: 0.1 | Q62: 0.05
A63: — Optimistic | B63: % | G63: 1.2 | H63: 0.9 | I63: 0.65 | J63: 0.5 | K63: 0.4 | L63: 0.35 | M63: 0.28 | N63: 0.22 | O63: 0.18 | P63: 0.13 | Q63: 0.06
A64: — Pessimistic | B64: % | G64: 0.8 | H64: 0.6 | I64: 0.4 | J64: 0.28 | K64: 0.2 | L64: 0.15 | M64: 0.12 | N64: 0.1 | O64: 0.08 | P64: 0.06 | Q64: 0.04
A65: Going Out — Base | B65: % | G65: 1 | H65: 0.7 | I65: 0.5 | J65: 0.35 | K65: 0.25 | L65: 0.2 | M65: 0.15 | N65: 0.12 | O65: 0.1 | P65: 0.08 | Q65: 0.05
A66: — Optimistic | B66: % | G66: 1.2 | H66: 0.85 | I66: 0.65 | J66: 0.5 | K66: 0.4 | L66: 0.3 | M66: 0.22 | N66: 0.18 | O66: 0.14 | P66: 0.1 | Q66: 0.06
A67: — Pessimistic | B67: % | G67: 0.8 | H67: 0.55 | I67: 0.35 | J67: 0.22 | K67: 0.15 | L67: 0.12 | M67: 0.1 | N67: 0.08 | O67: 0.06 | P67: 0.05 | Q67: 0.04
... A70: — Pessimistic | B70: % | G70: 0.08 | H70: 0.08 | I70: 0.05 | J70: 0.05 | K70: 0.05 | L70: 0.04 | M70: 0.04 | N70: 0.04 | O70: 0.04 | P70: 0.04 | Q70: 0.04
A72: Segment Result margin (% of segment revenue)
A73: Food Delivery — Base | B73: % | G73: 0.21 | H73: 0.22 | I73: 0.23 | J73: 0.24 | K73: 0.24 | L73: 0.25 | M73: 0.25 | N73: 0.25 | O73: 0.25 | P73: 0.25 | Q73: 0.25
A74: — Optimistic | B74: % | G74: 0.23 | H74: 0.24 | I74: 0.25 | J74: 0.26 | K74: 0.27 | L74: 0.28 | M74: 0.28 | N74: 0.28 | O74: 0.28 | P74: 0.28 | Q74: 0.28
A75: — Pessimistic | B75: % | G75: 0.19 | H75: 0.2 | I75: 0.2 | J75: 0.21 | K75: 0.21 | L75: 0.22 | M75: 0.22 | N75: 0.22 | O75: 0.22 | P75: 0.22 | Q75: 0.22
A76: Hyperpure (B2B supplies) — Base | B76: % | G76: 0.01 | H76: 0.02 | I76: 0.03 | J76: 0.04 | K76: 0.05 | L76: 0.05 | M76: 0.05 | N76: 0.05 | O76: 0.05 | P76: 0.05 | Q76: 0.05
A77: — Optimistic | B77: % | G77: 0.02 | H77: 0.03 | I77: 0.04 | J77: 0.05 | K77: 0.06 | L77: 0.07 | M77: 0.07 | N77: 0.07 | O77: 0.07 | P77: 0.07 | Q77: 0.07
A78: — Pessimistic | B78: % | G78: 0 | H78: 0 | I78: 0.01 | J78: 0.02 | K78: 0.02 | L78: 0.03 | M78: 0.03 | N78: 0.03 | O78: 0.03 | P78: 0.03 | Q78: 0.03
A79: Quick Commerce (Blinkit) — Base | B79: % | G79: 0.02 | H79: 0.05 | I79: 0.08 | J79: 0.1 | K79: 0.12 | L79: 0.13 | M79: 0.14 | N79: 0.15 | O79: 0.15 | P79: 0.15 | Q79: 0.15
A80: — Optimistic | B80: % | G80: 0.03 | H80: 0.07 | I80: 0.11 | J80: 0.14 | K80: 0.16 | L80: 0.17 | M80: 0.18 | N80: 0.19 | O80: 0.19 | P80: 0.19 | Q80: 0.19
A81: — Pessimistic | B81: % | G81: 0 | H81: 0.02 | I81: 0.04 | J81: 0.06 | K81: 0.08 | L81: 0.09 | M81: 0.1 | N81: 0.11 | O81: 0.11 | P81: 0.11 | Q81: 0.11
A82: Going Out — Base | B82: % | G82: -0.05 | H82: -0.02 | I82: 0.02 | J82: 0.05 | K82: 0.08 | L82: 0.1 | M82: 0.12 | N82: 0.14 | O82: 0.15 | P82: 0.15 | Q82: 0.15
A83: — Optimistic | B83: % | G83: -0.03 | H83: 0 | I83: 0.04 | J83: 0.08 | K83: 0.12 | L83: 0.15 | M83: 0.17 | N83: 0.18 | O83: 0.19 | P83: 0.19 | Q83: 0.19
A84: — Pessimistic | B84: % | G84: -0.08 | H84: -0.05 | I84: -0.02 | J84: 0 | K84: 0.03 | L84: 0.05 | M84: 0.07 | N84: 0.09 | O84: 0.1 | P84: 0.1 | Q84: 0.1
... A87: — Pessimistic | B87: % | G87: -0.4 | H87: -0.3 | I87: -0.2 | J87: -0.1 | K87: -0.05 | L87: 0 | M87: 0 | N87: 0 | O87: 0 | P87: 0 | Q87: 0
A89: Consolidated ratios (% of revenue unless stated)
A90: Share-based payment expense (SBP) — Base | B90: % | G90: 0.035 | H90: 0.03 | I90: 0.027 | J90: 0.025 | K90: 0.022 | L90: 0.02 | M90: 0.018 | N90: 0.017 | O90: 0.015 | P90: 0.015 | Q90: 0.015
A91: — Optimistic | B91: % | G91: 0.03 | H91: 0.025 | I91: 0.022 | J91: 0.02 | K91: 0.018 | L91: 0.015 | M91: 0.015 | N91: 0.015 | O91: 0.013 | P91: 0.013 | Q91: 0.013
A92: — Pessimistic | B92: % | G92: 0.04 | H92: 0.035 | I92: 0.03 | J92: 0.028 | K92: 0.025 | L92: 0.023 | M92: 0.022 | N92: 0.02 | O92: 0.018 | P92: 0.018 | Q92: 0.018
A93: Depreciation & amortisation (D&A) — Base | B93: % | G93: 0.043 | H93: 0.042 | I93: 0.04 | J93: 0.038 | K93: 0.037 | L93: 0.036 | M93: 0.035 | N93: 0.035 | O93: 0.035 | P93: 0.035 | Q93: 0.035
A94: — Optimistic | B94: % | G94: 0.04 | H94: 0.038 | I94: 0.036 | J94: 0.035 | K94: 0.034 | L94: 0.033 | M94: 0.033 | N94: 0.033 | O94: 0.033 | P94: 0.033 | Q94: 0.033
A95: — Pessimistic | B95: % | G95: 0.045 | H95: 0.044 | I95: 0.042 | J95: 0.04 | K95: 0.04 | L95: 0.04 | M95: 0.04 | N95: 0.04 | O95: 0.04 | P95: 0.04 | Q95: 0.04
A96: Capital expenditure (Capex) — Base | B96: % | G96: 0.055 | H96: 0.05 | I96: 0.045 | J96: 0.04 | K96: 0.038 | L96: 0.035 | M96: 0.035 | N96: 0.035 | O96: 0.035 | P96: 0.035 | Q96: 0.035
A97: — Optimistic | B97: % | G97: 0.05 | H97: 0.045 | I97: 0.04 | J97: 0.035 | K97: 0.033 | L97: 0.03 | M97: 0.03 | N97: 0.03 | O97: 0.03 | P97: 0.03 | Q97: 0.03
A98: — Pessimistic | B98: % | G98: 0.06 | H98: 0.055 | I98: 0.05 | J98: 0.045 | K98: 0.043 | L98: 0.04 | M98: 0.04 | N98: 0.04 | O98: 0.04 | P98: 0.04 | Q98: 0.04
A99: Change in NWC (% of Δ revenue) — Base | B99: % | G99: 0.08 | H99: 0.08 | I99: 0.07 | J99: 0.07 | K99: 0.06 | L99: 0.06 | M99: 0.05 | N99: 0.05 | O99: 0.05 | P99: 0.05 | Q99: 0.05
A100: — Optimistic | B100: % | G100: 0.07 | H100: 0.07 | I100: 0.06 | J100: 0.06 | K100: 0.05 | L100: 0.05 | M100: 0.05 | N100: 0.04 | O100: 0.04 | P100: 0.04 | Q100: 0.04
A101: — Pessimistic | B101: % | G101: 0.09 | H101: 0.09 | I101: 0.08 | J101: 0.08 | K101: 0.07 | L101: 0.07 | M101: 0.06 | N101: 0.06 | O101: 0.06 | P101: 0.06 | Q101: 0.06
... A107: — Pessimistic | B107: % | G107: 0.05 | H107: 0.04 | I107: 0.033 | J107: 0.027 | K107: 0.023 | L107: 0.02 | M107: 0.018 | N107: 0.016 | O107: 0.014 | P107: 0.012 | Q107: 0.01

Sheet Scenarios
A1: Eternal Limited (formerly Zomato Limited) — Scenario DCF Engines
A2: Three parallel FCFF DCFs running off Base / Optimistic / Pessimistic driver inputs from the Assumptions sheet. All values in INR crores unless stated.
A3: Active case: | B3: =Assumptions!T7 -> Optimistic Case | D3: (Toggle scenarios in Assumptions!T6 — 1=Base, 2=Opt, 3=Pess. Each block below is computed independently from its case inputs.)
A5: Particulars | B5: Unit | C5: FY25A | D5: FY26E | E5: FY27E | F5: FY28E | G5: FY29E | H5: FY30E | I5: FY31E | J5: FY32E | K5: FY33E | L5: FY34E | M5: FY35E | N5: Terminal
A6: BASE CASE
A8: SEGMENT REVENUE
A9: Food Delivery | B9: ₹ Cr | C9: =DCF!F7 -> 8080 | D9: =C9*(1+Assumptions!G56) -> 10100 | E9: =D9*(1+Assumptions!H56) -> 12322 | F9: =E9*(1+Assumptions!I56) -> 14663.18 | G9: =F9*(1+Assumptions!J56) -> 17155.921 | H9: =G9*(1+Assumptions!K56) -> 19729.309 | I9: =H9*(1+Assumptions!L56) -> 22294.119 | J9: =I9*(1+Assumptions!M56) -> 24969.413 | K9: =J9*(1+Assumptions!N56) -> 27716.049 | ... N9: =M9*(1+Assumptions!Q56) -> 34893.119
A10: Hyperpure (B2B supplies) | B10: ₹ Cr | C10: =DCF!F8 -> 6196 | D10: =C10*(1+Assumptions!G59) -> 10223.4 | E10: =D10*(1+Assumptions!H59) -> 15335.1 | F10: =E10*(1+Assumptions!I59) -> 21162.438 | G10: =F10*(1+Assumptions!J59) -> 27511.169 | H10: =G10*(1+Assumptions!K59) -> 34388.962 | I10: =H10*(1+Assumptions!L59) -> 41954.533 | J10: =I10*(1+Assumptions!M59) -> 49506.349 | K10: =J10*(1+Assumptions!N59) -> 56932.302 | ... N10: =M10*(1+Assumptions!Q59) -> 73647.626
A11: Quick Commerce (Blinkit) | B11: ₹ Cr | C11: =DCF!F9 -> 5206 | D11: =C11*(1+Assumptions!G62) -> 10412 | E11: =D11*(1+Assumptions!H62) -> 18221 | F11: =E11*(1+Assumptions!I62) -> 28242.55 | G11: =F11*(1+Assumptions!J62) -> 39539.57 | H11: =G11*(1+Assumptions!K62) -> 51401.441 | I11: =H11*(1+Assumptions!L62) -> 64251.801 | J11: =I11*(1+Assumptions!M62) -> 77102.161 | K11: =J11*(1+Assumptions!N62) -> 89438.507 | ... N11: =M11*(1+Assumptions!Q62) -> 116730.67
A12: Going Out | B12: ₹ Cr | C12: =DCF!F10 -> 737 | D12: =C12*(1+Assumptions!G65) -> 1474 | E12: =D12*(1+Assumptions!H65) -> 2505.8 | F12: =E12*(1+Assumptions!I65) -> 3758.7 | G12: =F12*(1+Assumptions!J65) -> 5074.245 | H12: =G12*(1+Assumptions!K65) -> 6342.8062 | I12: =H12*(1+Assumptions!L65) -> 7611.3675 | J12: =I12*(1+Assumptions!M65) -> 8753.0726 | K12: =J12*(1+Assumptions!N65) -> 9803.4413 | ... N12: =M12*(1+Assumptions!Q65) -> 12228.813
A13: All other segments | B13: ₹ Cr | C13: =DCF!F11 -> 24 | D13: =C13*(1+Assumptions!G68) -> 26.4 | E13: =D13*(1+Assumptions!H68) -> 29.04 | F13: =E13*(1+Assumptions!I68) -> 31.944 | G13: =F13*(1+Assumptions!J68) -> 34.49952 | H13: =G13*(1+Assumptions!K68) -> 37.259482 | I13: =H13*(1+Assumptions!L68) -> 39.122456 | J13: =I13*(1+Assumptions!M68) -> 41.078578 | K13: =J13*(1+Assumptions!N68) -> 43.132507 | ... N13: =M13*(1+Assumptions!Q68) -> 49.931269
A14: Total Revenue from Operations | B14: ₹ Cr | C14: =SUM(C9:C13) -> 20243 | D14: =SUM(D9:D13) -> 32235.8 | E14: =SUM(E9:E13) -> 48412.94 | F14: =SUM(F9:F13) -> 67858.812 | G14: =SUM(G9:G13) -> 89315.405 | H14: =SUM(H9:H13) -> 111899.78 | I14: =SUM(I9:I13) -> 136150.94 | J14: =SUM(J9:J13) -> 160372.08 | ... N14: =SUM(N9:N13) -> 237550.16
A15: YoY revenue growth | B15: % | D15: =D14/C14-1 -> 0.59244183 | E15: =E14/D14-1 -> 0.50183771 | F15: =F14/E14-1 -> 0.40166683 | G15: =G14/F14-1 -> 0.31619464 | H15: =H14/G14-1 -> 0.25286089 | I15: =I14/H14-1 -> 0.2167222 | J15: =J14/I14-1 -> 0.17789911 | K15: =K14/J14-1 -> 0.14691683 | ... N15: =N14/M14-1 -> 0.05
A17: SEGMENT RESULTS (≈ Adj. EBITDA)
A18: Food Delivery | B18: ₹ Cr | D18: =D9*Assumptions!G73 -> 2121 | E18: =E9*Assumptions!H73 -> 2710.84 | F18: =F9*Assumptions!I73 -> 3372.5314 | G18: =G9*Assumptions!J73 -> 4117.4209 | H18: =H9*Assumptions!K73 -> 4735.0341 | I18: =I9*Assumptions!L73 -> 5573.5297 | J18: =J9*Assumptions!M73 -> 6242.3533 | K18: =K9*Assumptions!N73 -> 6929.0121 | ... N18: =N9*Assumptions!Q73 -> 8723.2798
A19: Hyperpure (B2B supplies) | B19: ₹ Cr | D19: =D10*Assumptions!G76 -> 102.234 | E19: =E10*Assumptions!H76 -> 306.702 | F19: =F10*Assumptions!I76 -> 634.87314 | G19: =G10*Assumptions!J76 -> 1100.4468 | H19: =H10*Assumptions!K76 -> 1719.4481 | I19: =I10*Assumptions!L76 -> 2097.7267 | J19: =J10*Assumptions!M76 -> 2475.3175 | K19: =K10*Assumptions!N76 -> 2846.6151 | ... N19: =N10*Assumptions!Q76 -> 3682.3813
A20: Quick Commerce (Blinkit) | B20: ₹ Cr | D20: =D11*Assumptions!G79 -> 208.24 | E20: =E11*Assumptions!H79 -> 911.05 | F20: =F11*Assumptions!I79 -> 2259.404 | G20: =G11*Assumptions!J79 -> 3953.957 | H20: =H11*Assumptions!K79 -> 6168.1729 | I20: =I11*Assumptions!L79 -> 8352.7342 | J20: =J11*Assumptions!M79 -> 10794.303 | K20: =K11*Assumptions!N79 -> 13415.776 | ... N20: =N11*Assumptions!Q79 -> 17509.6
A21: Going Out | B21: ₹ Cr | D21: =D12*Assumptions!G82 -> -73.7 | E21: =E12*Assumptions!H82 -> -50.116 | F21: =F12*Assumptions!I82 -> 75.174 | G21: =G12*Assumptions!J82 -> 253.71225 | H21: =H12*Assumptions!K82 -> 507.4245 | I21: =I12*Assumptions!L82 -> 761.13675 | J21: =J12*Assumptions!M82 -> 1050.3687 | K21: =K12*Assumptions!N82 -> 1372.4818 | ... N21: =N12*Assumptions!Q82 -> 1834.3219
A22: All other segments | B22: ₹ Cr | D22: =D13*Assumptions!G85 -> -7.92 | E22: =E13*Assumptions!H85 -> -5.808 | F22: =F13*Assumptions!I85 -> -3.1944 | G22: =G13*Assumptions!J85 -> 0 | H22: =H13*Assumptions!K85 -> 1.8629741 | I22: =I13*Assumptions!L85 -> 1.9561228 | J22: =J13*Assumptions!M85 -> 2.0539289 | K22: =K13*Assumptions!N85 -> 2.1566254 | ... N22: =N13*Assumptions!Q85 -> 2.4965634
A23: Total Adj. EBITDA | B23: ₹ Cr | D23: =SUM(D18:D22) -> 2349.854 | E23: =SUM(E18:E22) -> 3872.668 | F23: =SUM(F18:F22) -> 6338.7881 | G23: =SUM(G18:G22) -> 9425.537 | H23: =SUM(H18:H22) -> 13131.943 | I23: =SUM(I18:I22) -> 16787.083 | J23: =SUM(J18:J22) -> 20564.396 | K23: =SUM(K18:K22) -> 24566.042 | ... N23: =SUM(N18:N22) -> 31752.08
A24: Adj. EBITDA margin | B24: % | D24: =D23/D14 -> 0.072895787 | E24: =E23/E14 -> 0.079992415 | F24: =F23/F14 -> 0.093411422 | G24: =G23/G14 -> 0.10553092 | H24: =H23/H14 -> 0.1173545 | I24: =I23/I14 -> 0.12329759 | J24: =J23/J14 -> 0.12822928 | K24: =K23/K14 -> 0.13355942 | ... N24: =N23/N14 -> 0.13366474
A26: Less: Share-based payment expense | B26: ₹ Cr | D26: =-D14*Assumptions!G90 -> -1128.253 | E26: =-E14*Assumptions!H90 -> -1452.3882 | F26: =-F14*Assumptions!I90 -> -1832.1879 | G26: =-G14*Assumptions!J90 -> -2232.8851 | H26: =-H14*Assumptions!K90 -> -2461.7951 | I26: =-I14*Assumptions!L90 -> -2723.0189 | J26: =-J14*Assumptions!M90 -> -2886.6974 | K26: =-K14*Assumptions!N90 -> -3126.8683 | ... N26: =-N14*Assumptions!Q90 -> -3563.2523
A27: Reported EBITDA | B27: ₹ Cr | D27: =D23+D26 -> 1221.601 | E27: =E23+E26 -> 2420.2798 | F27: =F23+F26 -> 4506.6002 | G27: =G23+G26 -> 7192.6519 | H27: =H23+H26 -> 10670.147 | I27: =I23+I26 -> 14064.065 | J27: =J23+J26 -> 17677.699 | K27: =K23+K26 -> 21439.173 | ... N27: =N23+N26 -> 28188.827
A28: Less: Depreciation & amortisation | B28: ₹ Cr | D28: =-D14*Assumptions!G93 -> -1386.1394 | E28: =-E14*Assumptions!H93 -> -2033.3435 | F28: =-F14*Assumptions!I93 -> -2714.3525 | G28: =-G14*Assumptions!J93 -> -3393.9854 | H28: =-H14*Assumptions!K93 -> -4140.2918 | I28: =-I14*Assumptions!L93 -> -4901.434 | J28: =-J14*Assumptions!M93 -> -5613.0226 | K28: =-K14*Assumptions!N93 -> -6437.6701 | ... N28: =-N14*Assumptions!Q93 -> -8314.2555
A29: EBIT | B29: ₹ Cr | D29: =D27+D28 -> -164.5384 | E29: =E27+E28 -> 386.93632 | F29: =F27+F28 -> 1792.2477 | G29: =G27+G28 -> 3798.6665 | H29: =H27+H28 -> 6529.8557 | I29: =I27+I28 -> 9162.6306 | J29: =J27+J28 -> 12064.676 | K29: =K27+K28 -> 15001.503 | ... N29: =N27+N28 -> 19874.572
A30: EBIT margin | B30: % | D30: =D29/D14 -> -0.0051042133 | E30: =E29/E14 -> 0.0079924153 | F30: =F29/F14 -> 0.026411422 | G30: =G29/G14 -> 0.042530922 | H30: =H29/H14 -> 0.058354501 | I30: =I29/I14 -> 0.067297592 | J30: =J29/J14 -> 0.075229282 | K30: =K29/K14 -> 0.081559416 | ... N30: =N29/N14 -> 0.083664739
A31: Less: Cash tax on EBIT | B31: ₹ Cr | D31: =-MAX(D29,0)*Assumptions!G102 -> 0 | E31: =-MAX(E29,0)*Assumptions!H102 -> 0 | F31: =-MAX(F29,0)*Assumptions!I102 -> -179.22477 | G31: =-MAX(G29,0)*Assumptions!J102 -> -683.75997 | H31: =-MAX(H29,0)*Assumptions!K102 -> -1436.5683 | I31: =-MAX(I29,0)*Assumptions!L102 -> -2308.9829 | J31: =-MAX(J29,0)*Assumptions!M102 -> -3040.2984 | K31: =-MAX(K29,0)*Assumptions!N102 -> -3780.3788 | ... N31: =-MAX(N29,0)*Assumptions!Q102 -> -5008.3921
A32: NOPAT | B32: ₹ Cr | D32: =D29+D31 -> -164.5384 | E32: =E29+E31 -> 386.93632 | F32: =F29+F31 -> 1613.023 | G32: =G29+G31 -> 3114.9065 | H32: =H29+H31 -> 5093.2875 | I32: =I29+I31 -> 6853.6477 | J32: =J29+J31 -> 9024.3777 | K32: =K29+K31 -> 11221.124 | ... N32: =N29+N31 -> 14866.18
A33: Plus: D&A (add-back) | B33: ₹ Cr | D33: =-D28 -> 1386.1394 | E33: =-E28 -> 2033.3435 | F33: =-F28 -> 2714.3525 | G33: =-G28 -> 3393.9854 | H33: =-H28 -> 4140.2918 | I33: =-I28 -> 4901.434 | J33: =-J28 -> 5613.0226 | K33: =-K28 -> 6437.6701 | ... N33: =-N28 -> 8314.2555
A34: Less: Capital expenditure | B34: ₹ Cr | D34: =-D14*Assumptions!G96 -> -1772.969 | E34: =-E14*Assumptions!H96 -> -2420.647 | F34: =-F14*Assumptions!I96 -> -3053.6465 | G34: =-G14*Assumptions!J96 -> -3572.6162 | H34: =-H14*Assumptions!K96 -> -4252.1915 | I34: =-I14*Assumptions!L96 -> -4765.283 | J34: =-J14*Assumptions!M96 -> -5613.0226 | K34: =-K14*Assumptions!N96 -> -6437.6701 | ... N34: =-N14*Assumptions!Q96 -> -8314.2555
A35: Less: Change in NWC | B35: ₹ Cr | D35: =-(D14-C14)*Assumptions!G99 -> -959.424 | E35: =-(E14-D14)*Assumptions!H99 -> -1294.1712 | F35: =-(F14-E14)*Assumptions!I99 -> -1361.211 | G35: =-(G14-F14)*Assumptions!J99 -> -1501.9615 | H35: =-(H14-G14)*Assumptions!K99 -> -1355.0624 | I35: =-(I14-H14)*Assumptions!L99 -> -1455.07 | J35: =-(J14-I14)*Assumptions!M99 -> -1211.0566 | K35: =-(K14-J14)*Assumptions!N99 -> -1178.0678 | ... N35: =-(N14-M14)*Assumptions!Q99 -> -565.59561
A36: Free Cash Flow to Firm (FCFF) | B36: ₹ Cr | D36: =D32+D33+D34+D35 -> -1510.792 | E36: =E32+E33+E34+E35 -> -1294.5384 | F36: =F32+F33+F34+F35 -> -87.482138 | G36: =G32+G33+G34+G35 -> 1434.3142 | H36: =H32+H33+H34+H35 -> 3626.3253 | I36: =I32+I33+I34+I35 -> 5534.7286 | J36: =J32+J33+J34+J35 -> 7813.3211 | K36: =K32+K33+K34+K35 -> 10043.057 | ... N36: =N32+N33+N34+N35 -> 14300.584
A37: FCFF margin | B37: % | D37: =D36/D14 -> -0.0468669 | E37: =E36/E14 -> -0.026739512 | F37: =F36/F14 -> -0.0012891787 | G37: =G36/G14 -> 0.016058979 | H37: =H36/H14 -> 0.032406904 | I37: =I36/I14 -> 0.040651416 | J37: =J36/J14 -> 0.04871996 | K37: =K36/K14 -> 0.054601584 | ... N37: =N36/N14 -> 0.060200273
A39: Forecast year (t) | B39: # | D39: 1 | E39: =D39+1 -> 2 | F39: =E39+1 -> 3 | G39: =F39+1 -> 4 | H39: =G39+1 -> 5 | I39: =H39+1 -> 6 | J39: =I39+1 -> 7 | K39: =J39+1 -> 8 | L39: =K39+1 -> 9 | M39: =L39+1 -> 10
A40: Discount factor | B40: x | D40: =1/(1+Assumptions!$T$24)^D39 -> 0.88478998 | E40: =1/(1+Assumptions!$T$24)^E39 -> 0.78285332 | F40: =1/(1+Assumptions!$T$24)^F39 -> 0.69266077 | G40: =1/(1+Assumptions!$T$24)^G39 -> 0.61285932 | H40: =1/(1+Assumptions!$T$24)^H39 -> 0.54225178 | I40: =1/(1+Assumptions!$T$24)^I39 -> 0.47977895 | J40: =1/(1+Assumptions!$T$24)^J39 -> 0.42450361 | K40: =1/(1+Assumptions!$T$24)^K39 -> 0.37559654 | ... M40: =1/(1+Assumptions!$T$24)^M39 -> 0.294037
A41: PV of FCFF | B41: ₹ Cr | D41: =D36*D40 -> -1336.7336 | E41: =E36*E40 -> -1013.4337 | F41: =F36*F40 -> -60.595445 | G41: =G36*G40 -> 879.03284 | H41: =H36*H40 -> 1966.3814 | I41: =I36*I40 -> 2655.4463 | J41: =J36*J40 -> 3316.783 | K41: =K36*K40 -> 3772.1373 | ... M41: =M36*M40 -> 3867.6672
A43: Sum of PV of explicit FCFF (FY26E–FY35E) | B43: ₹ Cr | D43: =SUM(D41:M41) -> 17973.636
A44: Terminal year FCFF (FY35E × (1+g)) | B44: ₹ Cr | D44: =M36*(1+Assumptions!$T$28) -> 13811.359
A45: Terminal Value (Gordon growth) | B45: ₹ Cr | D45: =D44/(Assumptions!$T$24-Assumptions!$T$28) -> 172186.32
A46: PV of Terminal Value | B46: ₹ Cr | D46: =D45/(1+Assumptions!$T$24)^Assumptions!$F$27 -> 50629.149
A47: Enterprise Value | B47: ₹ Cr | D47: =D43+D46 -> 68602.785
A48: Less: Total debt | B48: ₹ Cr | D48: =-Assumptions!$F$10 -> -2045
A49: Plus: Cash, bank balances & investments | B49: ₹ Cr | D49: =Assumptions!$F$11 -> 16806
A50: Equity Value | B50: ₹ Cr | D50: =D47+D48+D49 -> 83363.785
A51: Shares outstanding | B51: cr | D51: =Assumptions!$F$8 -> 951.5
A52: Implied per share value | B52: ₹ | D52: =D50/D51 -> 87.613016
A53: Current share price | B53: ₹ | D53: =Assumptions!$F$7 -> 251
A54: Implied upside / (downside) | B54: % | D54: =D52/D53-1 -> -0.65094416
A57: OPTIMISTIC CASE
A59: SEGMENT REVENUE
A60: Food Delivery | B60: ₹ Cr | C60: =DCF!F7 -> 8080 | D60: =C60*(1+Assumptions!G57) -> 10504 | E60: =D60*(1+Assumptions!H57) -> 13340.08 | F60: =E60*(1+Assumptions!I57) -> 16541.699 | G60: =F60*(1+Assumptions!J57) -> 20180.873 | H60: =G60*(1+Assumptions!K57) -> 24217.048 | I60: =H60*(1+Assumptions!L57) -> 28576.116 | J60: =I60*(1+Assumptions!M57) -> 33148.295 | K60: =J60*(1+Assumptions!N57) -> 37789.056 | ... N60: =M60*(1+Assumptions!Q57) -> 49349.484
A61: Hyperpure (B2B supplies) | B61: ₹ Cr | C61: =DCF!F8 -> 6196 | D61: =C61*(1+Assumptions!G60) -> 10843 | E61: =D61*(1+Assumptions!H60) -> 17348.8 | F61: =E61*(1+Assumptions!I60) -> 25676.224 | G61: =F61*(1+Assumptions!J60) -> 35946.714 | H61: =G61*(1+Assumptions!K60) -> 48528.063 | I61: =H61*(1+Assumptions!L60) -> 63086.482 | J61: =I61*(1+Assumptions!M60) -> 78858.103 | K61: =J61*(1+Assumptions!N60) -> 96206.886 | ... N61: =M61*(1+Assumptions!Q60) -> 138385.91
A62: Quick Commerce (Blinkit) | B62: ₹ Cr | C62: =DCF!F9 -> 5206 | D62: =C62*(1+Assumptions!G63) -> 11453.2 | E62: =D62*(1+Assumptions!H63) -> 21761.08 | F62: =E62*(1+Assumptions!I63) -> 35905.782 | G62: =F62*(1+Assumptions!J63) -> 53858.673 | H62: =G62*(1+Assumptions!K63) -> 75402.142 | I62: =H62*(1+Assumptions!L63) -> 101792.89 | J62: =I62*(1+Assumptions!M63) -> 130294.9 | K62: =J62*(1+Assumptions!N63) -> 158959.78 | ... N62: =M62*(1+Assumptions!Q63) -> 224674.39
A63: Going Out | B63: ₹ Cr | C63: =DCF!F10 -> 737 | D63: =C63*(1+Assumptions!G66) -> 1621.4 | E63: =D63*(1+Assumptions!H66) -> 2999.59 | F63: =E63*(1+Assumptions!I66) -> 4949.3235 | G63: =F63*(1+Assumptions!J66) -> 7423.9853 | H63: =G63*(1+Assumptions!K66) -> 10393.579 | I63: =H63*(1+Assumptions!L66) -> 13511.653 | J63: =I63*(1+Assumptions!M66) -> 16484.217 | K63: =J63*(1+Assumptions!N66) -> 19451.376 | ... N63: =M63*(1+Assumptions!Q66) -> 25855.547
A64: All other segments | B64: ₹ Cr | C64: =DCF!F11 -> 24 | D64: =C64*(1+Assumptions!G69) -> 27.6 | E64: =D64*(1+Assumptions!H69) -> 31.74 | F64: =E64*(1+Assumptions!I69) -> 36.501 | G64: =F64*(1+Assumptions!J69) -> 40.88112 | H64: =G64*(1+Assumptions!K69) -> 44.969232 | I64: =H64*(1+Assumptions!L69) -> 48.566771 | J64: =I64*(1+Assumptions!M69) -> 52.452112 | K64: =J64*(1+Assumptions!N69) -> 56.648281 | ... N64: =M64*(1+Assumptions!Q69) -> 70.039028
A65: Total Revenue from Operations | B65: ₹ Cr | C65: =SUM(C60:C64) -> 20243 | D65: =SUM(D60:D64) -> 34449.2 | E65: =SUM(E60:E64) -> 55481.29 | F65: =SUM(F60:F64) -> 83109.53 | G65: =SUM(G60:G64) -> 117451.13 | H65: =SUM(H60:H64) -> 158585.8 | I65: =SUM(I60:I64) -> 207015.71 | J65: =SUM(J60:J64) -> 258837.97 | ... N65: =SUM(N60:N64) -> 438335.37
A66: YoY revenue growth | B66: % | D66: =D65/C65-1 -> 0.70178333 | E66: =E65/D65-1 -> 0.61052477 | F66: =F65/E65-1 -> 0.497974 | G66: =G65/F65-1 -> 0.41320889 | H66: =H65/G65-1 -> 0.35022802 | I66: =I65/H65-1 -> 0.30538616 | J66: =J65/I65-1 -> 0.25033007 | K66: =K65/J65-1 -> 0.20717895 | ... N66: =N65/M65-1 -> 0.06
A68: SEGMENT RESULTS (≈ Adj. EBITDA)
A69: Food Delivery | B69: ₹ Cr | D69: =D60*Assumptions!G74 -> 2415.92 | E69: =E60*Assumptions!H74 -> 3201.6192 | F69: =F60*Assumptions!I74 -> 4135.4248 | G69: =G60*Assumptions!J74 -> 5247.027 | H69: =H60*Assumptions!K74 -> 6538.6029 | I69: =I60*Assumptions!L74 -> 8001.3125 | J69: =J60*Assumptions!M74 -> 9281.5225 | K69: =K60*Assumptions!N74 -> 10580.936 | ... N69: =N60*Assumptions!Q74 -> 13817.856
A70: Hyperpure (B2B supplies) | B70: ₹ Cr | D70: =D61*Assumptions!G77 -> 216.86 | E70: =E61*Assumptions!H77 -> 520.464 | F70: =F61*Assumptions!I77 -> 1027.049 | G70: =G61*Assumptions!J77 -> 1797.3357 | H70: =H61*Assumptions!K77 -> 2911.6838 | I70: =I61*Assumptions!L77 -> 4416.0538 | J70: =J61*Assumptions!M77 -> 5520.0672 | K70: =K61*Assumptions!N77 -> 6734.482 | ... N70: =N61*Assumptions!Q77 -> 9687.0136
A71: Quick Commerce (Blinkit) | B71: ₹ Cr | D71: =D62*Assumptions!G80 -> 343.596 | E71: =E62*Assumptions!H80 -> 1523.2756 | F71: =F62*Assumptions!I80 -> 3949.636 | G71: =G62*Assumptions!J80 -> 7540.2142 | H71: =H62*Assumptions!K80 -> 12064.343 | I71: =I62*Assumptions!L80 -> 17304.792 | J71: =J62*Assumptions!M80 -> 23453.082 | K71: =K62*Assumptions!N80 -> 30202.358 | ... N71: =N62*Assumptions!Q80 -> 42688.134
A72: Going Out | B72: ₹ Cr | D72: =D63*Assumptions!G83 -> -48.642 | E72: =E63*Assumptions!H83 -> 0 | F72: =F63*Assumptions!I83 -> 197.97294 | G72: =G63*Assumptions!J83 -> 593.91882 | H72: =H63*Assumptions!K83 -> 1247.2295 | I72: =I63*Assumptions!L83 -> 2026.748 | J72: =J63*Assumptions!M83 -> 2802.3169 | K72: =K63*Assumptions!N83 -> 3501.2477 | ... N72: =N63*Assumptions!Q83 -> 4912.5539
A73: All other segments | B73: ₹ Cr | D73: =D64*Assumptions!G86 -> -5.52 | E73: =E64*Assumptions!H86 -> -3.174 | F73: =F64*Assumptions!I86 -> 0 | G73: =G64*Assumptions!J86 -> 2.044056 | H73: =H64*Assumptions!K86 -> 3.5975386 | I73: =I64*Assumptions!L86 -> 3.8853416 | J73: =J64*Assumptions!M86 -> 4.196169 | K73: =K64*Assumptions!N86 -> 4.5318625 | ... N73: =N64*Assumptions!Q86 -> 5.6031223
A74: Total Adj. EBITDA | B74: ₹ Cr | D74: =SUM(D69:D73) -> 2922.214 | E74: =SUM(E69:E73) -> 5242.1848 | F74: =SUM(F69:F73) -> 9310.0827 | G74: =SUM(G69:G73) -> 15180.54 | H74: =SUM(H69:H73) -> 22765.456 | I74: =SUM(I69:I73) -> 31752.791 | J74: =SUM(J69:J73) -> 41061.185 | K74: =SUM(K69:K73) -> 51023.555 | ... N74: =SUM(N69:N73) -> 71111.16
A75: Adj. EBITDA margin | B75: % | D75: =D74/D65 -> 0.084826759 | E75: =E74/E65 -> 0.094485633 | F75: =F74/F65 -> 0.11202184 | G75: =G74/G65 -> 0.12924984 | H75: =H74/H65 -> 0.14355293 | I75: =I74/I65 -> 0.15338349 | J75: =J74/J65 -> 0.15863664 | K75: =K74/K65 -> 0.16329432 | ... N75: =N74/N65 -> 0.16223003
A77: Less: Share-based payment expense | B77: ₹ Cr | D77: =-D65*Assumptions!G91 -> -1033.476 | E77: =-E65*Assumptions!H91 -> -1387.0323 | F77: =-F65*Assumptions!I91 -> -1828.4097 | G77: =-G65*Assumptions!J91 -> -2349.0225 | H77: =-H65*Assumptions!K91 -> -2854.5444 | I77: =-I65*Assumptions!L91 -> -3105.2357 | J77: =-J65*Assumptions!M91 -> -3882.5695 | K77: =-K65*Assumptions!N91 -> -4686.9562 | ... N77: =-N65*Assumptions!Q91 -> -5698.3598
A78: Reported EBITDA | B78: ₹ Cr | D78: =D74+D77 -> 1888.738 | E78: =E74+E77 -> 3855.1525 | F78: =F74+F77 -> 7481.6731 | G78: =G74+G77 -> 12831.517 | H78: =H74+H77 -> 19910.912 | I78: =I74+I77 -> 28647.556 | J78: =J74+J77 -> 37178.616 | K78: =K74+K77 -> 46336.599 | ... N78: =N74+N77 -> 65412.8
A79: Less: Depreciation & amortisation | B79: ₹ Cr | D79: =-D65*Assumptions!G94 -> -1377.968 | E79: =-E65*Assumptions!H94 -> -2108.289 | F79: =-F65*Assumptions!I94 -> -2991.9431 | G79: =-G65*Assumptions!J94 -> -4110.7894 | H79: =-H65*Assumptions!K94 -> -5391.9173 | I79: =-I65*Assumptions!L94 -> -6831.5184 | J79: =-J65*Assumptions!M94 -> -8541.653 | K79: =-K65*Assumptions!N94 -> -10311.304 | ... N79: =-N65*Assumptions!Q94 -> -14465.067
A80: EBIT | B80: ₹ Cr | D80: =D78+D79 -> 510.77 | E80: =E78+E79 -> 1746.8635 | F80: =F78+F79 -> 4489.73 | G80: =G78+G79 -> 8720.7278 | H80: =H78+H79 -> 14518.995 | I80: =I78+I79 -> 21816.037 | J80: =J78+J79 -> 28636.963 | K80: =K78+K79 -> 36025.296 | ... N80: =N78+N79 -> 50947.733
A81: EBIT margin | B81: % | D81: =D80/D65 -> 0.014826759 | E81: =E80/E65 -> 0.031485633 | F81: =F80/F65 -> 0.054021843 | G81: =G80/G65 -> 0.074249844 | H81: =H80/H65 -> 0.09155293 | I81: =I80/I65 -> 0.10538349 | J81: =J80/J65 -> 0.11063664 | K81: =K80/K65 -> 0.11529432 | ... N81: =N80/N65 -> 0.11623003
A82: Less: Cash tax on EBIT | B82: ₹ Cr | D82: =-MAX(D80,0)*Assumptions!G103 -> 0 | E82: =-MAX(E80,0)*Assumptions!H103 -> 0 | F82: =-MAX(F80,0)*Assumptions!I103 -> -359.1784 | G82: =-MAX(G80,0)*Assumptions!J103 -> -1308.1092 | H82: =-MAX(H80,0)*Assumptions!K103 -> -2903.799 | I82: =-MAX(I80,0)*Assumptions!L103 -> -5497.6414 | J82: =-MAX(J80,0)*Assumptions!M103 -> -7216.5146 | K82: =-MAX(K80,0)*Assumptions!N103 -> -9078.3745 | ... N82: =-MAX(N80,0)*Assumptions!Q103 -> -12838.829
A83: NOPAT | B83: ₹ Cr | D83: =D80+D82 -> 510.77 | E83: =E80+E82 -> 1746.8635 | F83: =F80+F82 -> 4130.5516 | G83: =G80+G82 -> 7412.6187 | H83: =H80+H82 -> 11615.196 | I83: =I80+I82 -> 16318.396 | J83: =J80+J82 -> 21420.448 | K83: =K80+K82 -> 26946.921 | ... N83: =N80+N82 -> 38108.904
A84: Plus: D&A (add-back) | B84: ₹ Cr | D84: =-D79 -> 1377.968 | E84: =-E79 -> 2108.289 | F84: =-F79 -> 2991.9431 | G84: =-G79 -> 4110.7894 | H84: =-H79 -> 5391.9173 | I84: =-I79 -> 6831.5184 | J84: =-J79 -> 8541.653 | K84: =-K79 -> 10311.304 | ... N84: =-N79 -> 14465.067
A85: Less: Capital expenditure | B85: ₹ Cr | D85: =-D65*Assumptions!G97 -> -1722.46 | E85: =-E65*Assumptions!H97 -> -2496.6581 | F85: =-F65*Assumptions!I97 -> -3324.3812 | G85: =-G65*Assumptions!J97 -> -4110.7894 | H85: =-H65*Assumptions!K97 -> -5233.3315 | I85: =-I65*Assumptions!L97 -> -6210.4713 | J85: =-J65*Assumptions!M97 -> -7765.1391 | K85: =-K65*Assumptions!N97 -> -9373.9124 | ... N85: =-N65*Assumptions!Q97 -> -13150.061
A86: Less: Change in NWC | B86: ₹ Cr | D86: =-(D65-C65)*Assumptions!G100 -> -994.434 | E86: =-(E65-D65)*Assumptions!H100 -> -1472.2463 | F86: =-(F65-E65)*Assumptions!I100 -> -1657.6944 | G86: =-(G65-F65)*Assumptions!J100 -> -2060.4958 | H86: =-(H65-G65)*Assumptions!K100 -> -2056.7338 | I86: =-(I65-H65)*Assumptions!L100 -> -2421.4954 | J86: =-(J65-I65)*Assumptions!M100 -> -2591.1129 | K86: =-(K65-J65)*Assumptions!N100 -> -2145.0311 | ... N86: =-(N65-M65)*Assumptions!Q100 -> -992.45744
A87: Free Cash Flow to Firm (FCFF) | B87: ₹ Cr | D87: =D83+D84+D85+D86 -> -828.156 | E87: =E83+E84+E85+E86 -> -113.7518 | F87: =F83+F84+F85+F86 -> 2140.4191 | G87: =G83+G84+G85+G86 -> 5352.1229 | H87: =H83+H84+H85+H86 -> 9717.0478 | I87: =I83+I84+I85+I86 -> 14517.947 | J87: =J83+J84+J85+J86 -> 19605.849 | K87: =K83+K84+K85+K86 -> 25739.281 | ... N87: =N83+N84+N85+N86 -> 38431.453
A88: FCFF margin | B88: % | D88: =D87/D65 -> -0.02403992 | E88: =E87/E65 -> -0.0020502732 | F88: =F87/F65 -> 0.025754196 | G88: =G87/G65 -> 0.045568936 | H88: =H87/H65 -> 0.061273126 | I88: =I87/I65 -> 0.070129689 | J88: =J87/J65 -> 0.075745646 | K88: =K87/K65 -> 0.082375257 | ... N88: =N87/N65 -> 0.087675912
A90: Forecast year (t) | B90: # | D90: 1 | E90: =D90+1 -> 2 | F90: =E90+1 -> 3 | G90: =F90+1 -> 4 | H90: =G90+1 -> 5 | I90: =H90+1 -> 6 | J90: =I90+1 -> 7 | K90: =J90+1 -> 8 | L90: =K90+1 -> 9 | M90: =L90+1 -> 10
A91: Discount factor | B91: x | D91: =1/(1+Assumptions!$U$24)^D90 -> 0.89271951 | E91: =1/(1+Assumptions!$U$24)^E90 -> 0.79694813 | F91: =1/(1+Assumptions!$U$24)^F90 -> 0.71145115 | G91: =1/(1+Assumptions!$U$24)^G90 -> 0.63512632 | H91: =1/(1+Assumptions!$U$24)^H90 -> 0.56698966 | I91: =1/(1+Assumptions!$U$24)^I90 -> 0.50616273 | J91: =1/(1+Assumptions!$U$24)^J90 -> 0.45186135 | K91: =1/(1+Assumptions!$U$24)^K90 -> 0.40338544 | ... M91: =1/(1+Assumptions!$U$24)^M90 -> 0.32147727
A92: PV of FCFF | B92: ₹ Cr | D92: =D87*D91 -> -739.31102 | E92: =E87*E91 -> -90.654284 | F92: =F87*F91 -> 1522.8036 | G92: =G87*G91 -> 3399.2741 | H92: =H87*H91 -> 5509.4656 | I92: =I87*I91 -> 7348.444 | J92: =J87*J91 -> 8859.1254 | K92: =K87*K91 -> 10382.851 | ... M92: =M87*M91 -> 11340.965
A94: Sum of PV of explicit FCFF (FY26E–FY35E) | B94: ₹ Cr | D94: =SUM(D92:M92) -> 58699.654
A95: Terminal year FCFF (FY35E × (1+g)) | B95: ₹ Cr | D95: =M87*(1+Assumptions!$U$28) -> 37394.317
A96: Terminal Value (Gordon growth) | B96: ₹ Cr | D96: =D95/(Assumptions!$U$24-Assumptions!$U$28) -> 621450.19
A97: PV of Terminal Value | B97: ₹ Cr | D97: =D96/(1+Assumptions!$U$24)^Assumptions!$F$27 -> 199782.11
A98: Enterprise Value | B98: ₹ Cr | D98: =D94+D97 -> 258481.77
A99: Less: Total debt | B99: ₹ Cr | D99: =-Assumptions!$F$10 -> -2045
A100: Plus: Cash, bank balances & investments | B100: ₹ Cr | D100: =Assumptions!$F$11 -> 16806
A101: Equity Value | B101: ₹ Cr | D101: =D98+D99+D100 -> 273242.77
A102: Shares outstanding | B102: cr | D102: =Assumptions!$F$8 -> 951.5
A103: Implied per share value | B103: ₹ | D103: =D101/D102 -> 287.17054
A104: Current share price | B104: ₹ | D104: =Assumptions!$F$7 -> 251
A105: Implied upside / (downside) | B105: % | D105: =D103/D104-1 -> 0.14410573
A108: PESSIMISTIC CASE
A110: SEGMENT REVENUE
A111: Food Delivery | B111: ₹ Cr | C111: =DCF!F7 -> 8080 | D111: =C111*(1+Assumptions!G58) -> 9696 | E111: =D111*(1+Assumptions!H58) -> 11344.32 | F111: =E111*(1+Assumptions!I58) -> 12932.525 | G111: =F111*(1+Assumptions!J58) -> 14484.428 | H111: =G111*(1+Assumptions!K58) -> 15932.871 | I111: =H111*(1+Assumptions!L58) -> 17366.829 | J111: =I111*(1+Assumptions!M58) -> 18756.175 | K111: =J111*(1+Assumptions!N58) -> 20069.107 | ... N111: =M111*(1+Assumptions!Q58) -> 23230.393
A112: Hyperpure (B2B supplies) | B112: ₹ Cr | C112: =DCF!F8 -> 6196 | D112: =C112*(1+Assumptions!G61) -> 9294 | E112: =D112*(1+Assumptions!H61) -> 13011.6 | F112: =E112*(1+Assumptions!I61) -> 16654.848 | G112: =F112*(1+Assumptions!J61) -> 20318.915 | H112: =G112*(1+Assumptions!K61) -> 23976.319 | I112: =H112*(1+Assumptions!L61) -> 27572.767 | J112: =I112*(1+Assumptions!M61) -> 30881.499 | K112: =J112*(1+Assumptions!N61) -> 33969.649 | ... N112: =M112*(1+Assumptions!Q61) -> 40443.992
A113: Quick Commerce (Blinkit) | B113: ₹ Cr | C113: =DCF!F9 -> 5206 | D113: =C113*(1+Assumptions!G64) -> 9370.8 | E113: =D113*(1+Assumptions!H64) -> 14993.28 | F113: =E113*(1+Assumptions!I64) -> 20990.592 | G113: =F113*(1+Assumptions!J64) -> 26867.958 | H113: =G113*(1+Assumptions!K64) -> 32241.549 | I113: =H113*(1+Assumptions!L64) -> 37077.782 | J113: =I113*(1+Assumptions!M64) -> 41527.116 | K113: =J113*(1+Assumptions!N64) -> 45679.827 | ... N113: =M113*(1+Assumptions!Q64) -> 54386.037
A114: Going Out | B114: ₹ Cr | C114: =DCF!F10 -> 737 | D114: =C114*(1+Assumptions!G67) -> 1326.6 | E114: =D114*(1+Assumptions!H67) -> 2056.23 | F114: =E114*(1+Assumptions!I67) -> 2775.9105 | G114: =F114*(1+Assumptions!J67) -> 3386.6108 | H114: =G114*(1+Assumptions!K67) -> 3894.6024 | I114: =H114*(1+Assumptions!L67) -> 4361.9547 | J114: =I114*(1+Assumptions!M67) -> 4798.1502 | K114: =J114*(1+Assumptions!N67) -> 5182.0022 | ... N114: =M114*(1+Assumptions!Q67) -> 5998.2712
A115: All other segments | B115: ₹ Cr | C115: =DCF!F11 -> 24 | D115: =C115*(1+Assumptions!G70) -> 25.92 | E115: =D115*(1+Assumptions!H70) -> 27.9936 | F115: =E115*(1+Assumptions!I70) -> 29.39328 | G115: =F115*(1+Assumptions!J70) -> 30.862944 | H115: =G115*(1+Assumptions!K70) -> 32.406091 | I115: =H115*(1+Assumptions!L70) -> 33.702335 | J115: =I115*(1+Assumptions!M70) -> 35.050428 | K115: =J115*(1+Assumptions!N70) -> 36.452445 | ... N115: =M115*(1+Assumptions!Q70) -> 41.004044
A116: Total Revenue from Operations | B116: ₹ Cr | C116: =SUM(C111:C115) -> 20243 | D116: =SUM(D111:D115) -> 29713.32 | E116: =SUM(E111:E115) -> 41433.424 | F116: =SUM(F111:F115) -> 53383.269 | G116: =SUM(G111:G115) -> 65088.774 | H116: =SUM(H111:H115) -> 76077.748 | I116: =SUM(I111:I115) -> 86413.035 | J116: =SUM(J111:J115) -> 95997.99 | ... N116: =SUM(N111:N115) -> 124099.7
...

Sheet DCF
A1: Eternal Limited — DCF Valuation Model
A2: FCFF approach. Forecast FY26E–FY35E + Gordon growth terminal value. All values in INR crores.
A3: Active case: | B3: =Assumptions!T7 -> Optimistic Case | D3: WACC | E3: =Assumptions!F24 -> 0.12017267 | F3: Term g | G3: =Assumptions!F28 -> 0.06 | H3: Implied / share | I3: =F54 -> 287.17054 | J3: Upside | K3: =F56 -> 0.14410573
A5: Particulars | B5: Unit | C5: FY22A | D5: FY23A | E5: FY24A | F5: FY25A | G5: FY26E | H5: FY27E | I5: FY28E | J5: FY29E | K5: FY30E | L5: FY31E | M5: FY32E | N5: FY33E | O5: FY34E | P5: FY35E | Q5: Terminal
A6: SEGMENT REVENUE
A7: Food Delivery | B7: ₹ Cr | E7: 6361 | F7: 8080 | G7: =F7*(1+Assumptions!G32) -> 10504 | H7: =G7*(1+Assumptions!H32) -> 13340.08 | I7: =H7*(1+Assumptions!I32) -> 16541.699 | J7: =I7*(1+Assumptions!J32) -> 20180.873 | K7: =J7*(1+Assumptions!K32) -> 24217.048 | L7: =K7*(1+Assumptions!L32) -> 28576.116 | M7: =L7*(1+Assumptions!M32) -> 33148.295 | N7: =M7*(1+Assumptions!N32) -> 37789.056 | ... Q7: =P7*(1+Assumptions!Q32) -> 49349.484
A8: Hyperpure (B2B supplies) | B8: ₹ Cr | E8: 3172 | F8: 6196 | G8: =F8*(1+Assumptions!G33) -> 10843 | H8: =G8*(1+Assumptions!H33) -> 17348.8 | I8: =H8*(1+Assumptions!I33) -> 25676.224 | J8: =I8*(1+Assumptions!J33) -> 35946.714 | K8: =J8*(1+Assumptions!K33) -> 48528.063 | L8: =K8*(1+Assumptions!L33) -> 63086.482 | M8: =L8*(1+Assumptions!M33) -> 78858.103 | N8: =M8*(1+Assumptions!N33) -> 96206.886 | ... Q8: =P8*(1+Assumptions!Q33) -> 138385.91
A9: Quick Commerce (Blinkit) | B9: ₹ Cr | E9: 2301 | F9: 5206 | G9: =F9*(1+Assumptions!G34) -> 11453.2 | H9: =G9*(1+Assumptions!H34) -> 21761.08 | I9: =H9*(1+Assumptions!I34) -> 35905.782 | J9: =I9*(1+Assumptions!J34) -> 53858.673 | K9: =J9*(1+Assumptions!K34) -> 75402.142 | L9: =K9*(1+Assumptions!L34) -> 101792.89 | M9: =L9*(1+Assumptions!M34) -> 130294.9 | N9: =M9*(1+Assumptions!N34) -> 158959.78 | ... Q9: =P9*(1+Assumptions!Q34) -> 224674.39
A10: Going Out | B10: ₹ Cr | E10: 258 | F10: 737 | G10: =F10*(1+Assumptions!G35) -> 1621.4 | H10: =G10*(1+Assumptions!H35) -> 2999.59 | I10: =H10*(1+Assumptions!I35) -> 4949.3235 | J10: =I10*(1+Assumptions!J35) -> 7423.9853 | K10: =J10*(1+Assumptions!K35) -> 10393.579 | L10: =K10*(1+Assumptions!L35) -> 13511.653 | M10: =L10*(1+Assumptions!M35) -> 16484.217 | N10: =M10*(1+Assumptions!N35) -> 19451.376 | ... Q10: =P10*(1+Assumptions!Q35) -> 25855.547
A11: All other segments | B11: ₹ Cr | E11: 22 | F11: 24 | G11: =F11*(1+Assumptions!G36) -> 27.6 | H11: =G11*(1+Assumptions!H36) -> 31.74 | I11: =H11*(1+Assumptions!I36) -> 36.501 | J11: =I11*(1+Assumptions!J36) -> 40.88112 | K11: =J11*(1+Assumptions!K36) -> 44.969232 | L11: =K11*(1+Assumptions!L36) -> 48.566771 | M11: =L11*(1+Assumptions!M36) -> 52.452112 | N11: =M11*(1+Assumptions!N36) -> 56.648281 | ... Q11: =P11*(1+Assumptions!Q36) -> 70.039028
A12: Total Revenue from Operations | B12: ₹ Cr | C12: ='P&L'!C6 -> 4192.4 | D12: ='P&L'!D6 -> 7079.4 | E12: ='P&L'!E6 -> 12114 | F12: ='P&L'!F6 -> 20243 | G12: =SUM(G7:G11) -> 34449.2 | H12: =SUM(H7:H11) -> 55481.29 | I12: =SUM(I7:I11) -> 83109.53 | J12: =SUM(J7:J11) -> 117451.13 | K12: =SUM(K7:K11) -> 158585.8 | L12: =SUM(L7:L11) -> 207015.71 | M12: =SUM(M7:M11) -> 258837.97 | N12: =SUM(N7:N11) -> 312463.75 | ... Q12: =SUM(Q7:Q11) -> 438335.37
A13: YoY revenue growth | B13: % | D13: =D12/C12-1 -> 0.68862704 | E13: =E12/D12-1 -> 0.71116196 | F13: =F12/E12-1 -> 0.67104177 | G13: =G12/F12-1 -> 0.70178333 | H13: =H12/G12-1 -> 0.61052477 | I13: =I12/H12-1 -> 0.497974 | J13: =J12/I12-1 -> 0.41320889 | K13: =K12/J12-1 -> 0.35022802 | ... Q13: =Q12/P12-1 -> 0.06
A15: SEGMENT RESULTS (≈ Adj. EBITDA)
A16: Food Delivery | B16: ₹ Cr | E16: 935 | F16: 1541 | G16: =G7*Assumptions!G39 -> 2415.92 | H16: =H7*Assumptions!H39 -> 3201.6192 | I16: =I7*Assumptions!I39 -> 4135.4248 | J16: =J7*Assumptions!J39 -> 5247.027 | K16: =K7*Assumptions!K39 -> 6538.6029 | L16: =L7*Assumptions!L39 -> 8001.3125 | M16: =M7*Assumptions!M39 -> 9281.5225 | N16: =N7*Assumptions!N39 -> 10580.936 | ... Q16: =Q7*Assumptions!Q39 -> 13817.856
A17: Hyperpure (B2B supplies) | B17: ₹ Cr | E17: -100 | F17: -43 | G17: =G8*Assumptions!G40 -> 216.86 | H17: =H8*Assumptions!H40 -> 520.464 | I17: =I8*Assumptions!I40 -> 1027.049 | J17: =J8*Assumptions!J40 -> 1797.3357 | K17: =K8*Assumptions!K40 -> 2911.6838 | L17: =L8*Assumptions!L40 -> 4416.0538 | M17: =M8*Assumptions!M40 -> 5520.0672 | N17: =N8*Assumptions!N40 -> 6734.482 | ... Q17: =Q8*Assumptions!Q40 -> 9687.0136
A18: Quick Commerce (Blinkit) | B18: ₹ Cr | E18: -253 | F18: -21 | G18: =G9*Assumptions!G41 -> 343.596 | H18: =H9*Assumptions!H41 -> 1523.2756 | I18: =I9*Assumptions!I41 -> 3949.636 | J18: =J9*Assumptions!J41 -> 7540.2142 | K18: =K9*Assumptions!K41 -> 12064.343 | L18: =L9*Assumptions!L41 -> 17304.792 | M18: =M9*Assumptions!M41 -> 23453.082 | N18: =N9*Assumptions!N41 -> 30202.358 | ... Q18: =Q9*Assumptions!Q41 -> 42688.134
A19: Going Out | B19: ₹ Cr | E19: -2 | F19: -30 | G19: =G10*Assumptions!G42 -> -48.642 | H19: =H10*Assumptions!H42 -> 0 | I19: =I10*Assumptions!I42 -> 197.97294 | J19: =J10*Assumptions!J42 -> 593.91882 | K19: =K10*Assumptions!K42 -> 1247.2295 | L19: =L10*Assumptions!L42 -> 2026.748 | M19: =M10*Assumptions!M42 -> 2802.3169 | N19: =N10*Assumptions!N42 -> 3501.2477 | ... Q19: =Q10*Assumptions!Q42 -> 4912.5539
A20: All other segments | B20: ₹ Cr | E20: -23 | F20: -12 | G20: =G11*Assumptions!G43 -> -5.52 | H20: =H11*Assumptions!H43 -> -3.174 | I20: =I11*Assumptions!I43 -> 0 | J20: =J11*Assumptions!J43 -> 2.044056 | K20: =K11*Assumptions!K43 -> 3.5975386 | L20: =L11*Assumptions!L43 -> 3.8853416 | M20: =M11*Assumptions!M43 -> 4.196169 | N20: =N11*Assumptions!N43 -> 4.5318625 | ... Q20: =Q11*Assumptions!Q43 -> 5.6031223
A21: Total Adj. EBITDA | B21: ₹ Cr | E21: =SUM(E16:E20) -> 557 | F21: =SUM(F16:F20) -> 1435 | G21: =SUM(G16:G20) -> 2922.214 | H21: =SUM(H16:H20) -> 5242.1848 | I21: =SUM(I16:I20) -> 9310.0827 | J21: =SUM(J16:J20) -> 15180.54 | K21: =SUM(K16:K20) -> 22765.456 | L21: =SUM(L16:L20) -> 31752.791 | ... Q21: =SUM(Q16:Q20) -> 71111.16
A22: Adj. EBITDA margin | B22: % | E22: =E21/E12 -> 0.045979858 | F22: =F21/F12 -> 0.070888702 | G22: =G21/G12 -> 0.084826759 | H22: =H21/H12 -> 0.094485633 | I22: =I21/I12 -> 0.11202184 | J22: =J21/J12 -> 0.12924984 | K22: =K21/K12 -> 0.14355293 | L22: =L21/L12 -> 0.15338349 | ... Q22: =Q21/Q12 -> 0.16223003
A25: Total Adj. EBITDA (segment results) | B25: ₹ Cr | E25: =E21 -> 557 | F25: =F21 -> 1435 | G25: =G21 -> 2922.214 | H25: =H21 -> 5242.1848 | I25: =I21 -> 9310.0827 | J25: =J21 -> 15180.54 | K25: =K21 -> 22765.456 | L25: =L21 -> 31752.791 | ... Q25: =Q21 -> 71111.16
A26: Less: Share-based payment expense | B26: ₹ Cr | E26: =-Equity!E29 -> 515 | F26: =-Equity!F29 -> -798 | G26: =-G12*Assumptions!G46 -> -1033.476 | H26: =-H12*Assumptions!H46 -> -1387.0323 | I26: =-I12*Assumptions!I46 -> -1828.4097 | J26: =-J12*Assumptions!J46 -> -2349.0225 | K26: =-K12*Assumptions!K46 -> -2854.5444 | L26: =-L12*Assumptions!L46 -> -3105.2357 | M26: =-M12*Assumptions!M46 -> -3882.5695 | N26: =-N12*Assumptions!N46 -> -4686.9562 | ... Q26: =-Q12*Assumptions!Q46 -> -5698.3598
A27: Reported EBITDA | B27: ₹ Cr | E27: =E25+E26 -> 1072 | F27: =F25+F26 -> 637 | G27: =G25+G26 -> 1888.738 | H27: =H25+H26 -> 3855.1525 | I27: =I25+I26 -> 7481.6731 | J27: =J25+J26 -> 12831.517 | K27: =K25+K26 -> 19910.912 | L27: =L25+L26 -> 28647.556 | ... Q27: =Q25+Q26 -> 65412.8
A28: Less: Depreciation & amortisation | B28: ₹ Cr | C28: =-'P&L'!C14 -> -150.3 | D28: =-'P&L'!D14 -> -436.9 | E28: =-'P&L'!E14 -> -526 | F28: =-'P&L'!F14 -> -863 | G28: =-G12*Assumptions!G47 -> -1377.968 | H28: =-H12*Assumptions!H47 -> -2108.289 | I28: =-I12*Assumptions!I47 -> -2991.9431 | J28: =-J12*Assumptions!J47 -> -4110.7894 | K28: =-K12*Assumptions!K47 -> -5391.9173 | L28: =-L12*Assumptions!L47 -> -6831.5184 | M28: =-M12*Assumptions!M47 -> -8541.653 | N28: =-N12*Assumptions!N47 -> -10311.304 | ... Q28: =-Q12*Assumptions!Q47 -> -14465.067
A29: EBIT | B29: ₹ Cr | E29: =E27+E28 -> 546 | F29: =F27+F28 -> -226 | G29: =G27+G28 -> 510.77 | H29: =H27+H28 -> 1746.8635 | I29: =I27+I28 -> 4489.73 | J29: =J27+J28 -> 8720.7278 | K29: =K27+K28 -> 14518.995 | L29: =L27+L28 -> 21816.037 | ... Q29: =Q27+Q28 -> 50947.733
A30: EBIT margin | B30: % | E30: =E29/E12 -> 0.045071818 | F30: =F29/F12 -> -0.011164353 | G30: =G29/G12 -> 0.014826759 | H30: =H29/H12 -> 0.031485633 | I30: =I29/I12 -> 0.054021843 | J30: =J29/J12 -> 0.074249844 | K30: =K29/K12 -> 0.09155293 | L30: =L29/L12 -> 0.10538349 | ... Q30: =Q29/Q12 -> 0.11623003
A31: Less: Cash tax on EBIT | B31: ₹ Cr | G31: =-MAX(G29,0)*Assumptions!G50 -> 0 | H31: =-MAX(H29,0)*Assumptions!H50 -> 0 | I31: =-MAX(I29,0)*Assumptions!I50 -> -359.1784 | J31: =-MAX(J29,0)*Assumptions!J50 -> -1308.1092 | K31: =-MAX(K29,0)*Assumptions!K50 -> -2903.799 | L31: =-MAX(L29,0)*Assumptions!L50 -> -5497.6414 | M31: =-MAX(M29,0)*Assumptions!M50 -> -7216.5146 | N31: =-MAX(N29,0)*Assumptions!N50 -> -9078.3745 | ... Q31: =-MAX(Q29,0)*Assumptions!Q50 -> -12838.829
A32: NOPAT | B32: ₹ Cr | G32: =G29+G31 -> 510.77 | H32: =H29+H31 -> 1746.8635 | I32: =I29+I31 -> 4130.5516 | J32: =J29+J31 -> 7412.6187 | K32: =K29+K31 -> 11615.196 | L32: =L29+L31 -> 16318.396 | M32: =M29+M31 -> 21420.448 | N32: =N29+N31 -> 26946.921 | ... Q32: =Q29+Q31 -> 38108.904
A33: Plus: D&A (add-back) | B33: ₹ Cr | G33: =-G28 -> 1377.968 | H33: =-H28 -> 2108.289 | I33: =-I28 -> 2991.9431 | J33: =-J28 -> 4110.7894 | K33: =-K28 -> 5391.9173 | L33: =-L28 -> 6831.5184 | M33: =-M28 -> 8541.653 | N33: =-N28 -> 10311.304 | ... Q33: =-Q28 -> 14465.067
A34: Less: Capital expenditure | B34: ₹ Cr | G34: =-G12*Assumptions!G48 -> -1722.46 | H34: =-H12*Assumptions!H48 -> -2496.6581 | I34: =-I12*Assumptions!I48 -> -3324.3812 | J34: =-J12*Assumptions!J48 -> -4110.7894 | K34: =-K12*Assumptions!K48 -> -5233.3315 | L34: =-L12*Assumptions!L48 -> -6210.4713 | M34: =-M12*Assumptions!M48 -> -7765.1391 | N34: =-N12*Assumptions!N48 -> -9373.9124 | ... Q34: =-Q12*Assumptions!Q48 -> -13150.061
A35: Less: Change in NWC | B35: ₹ Cr | G35: =-(G12-F12)*Assumptions!G49 -> -994.434 | H35: =-(H12-G12)*Assumptions!H49 -> -1472.2463 | I35: =-(I12-H12)*Assumptions!I49 -> -1657.6944 | J35: =-(J12-I12)*Assumptions!J49 -> -2060.4958 | K35: =-(K12-J12)*Assumptions!K49 -> -2056.7338 | L35: =-(L12-K12)*Assumptions!L49 -> -2421.4954 | M35: =-(M12-L12)*Assumptions!M49 -> -2591.1129 | N35: =-(N12-M12)*Assumptions!N49 -> -2145.0311 | ... Q35: =-(Q12-P12)*Assumptions!Q49 -> -992.45744
A36: Free Cash Flow to Firm (FCFF) | B36: ₹ Cr | G36: =G32+G33+G34+G35 -> -828.156 | H36: =H32+H33+H34+H35 -> -113.7518 | I36: =I32+I33+I34+I35 -> 2140.4191 | J36: =J32+J33+J34+J35 -> 5352.1229 | K36: =K32+K33+K34+K35 -> 9717.0478 | L36: =L32+L33+L34+L35 -> 14517.947 | M36: =M32+M33+M34+M35 -> 19605.849 | N36: =N32+N33+N34+N35 -> 25739.281 | ... Q36: =Q32+Q33+Q34+Q35 -> 38431.453
A37: FCFF margin | B37: % | G37: =G36/G12 -> -0.02403992 | H37: =H36/H12 -> -0.0020502732 | I37: =I36/I12 -> 0.025754196 | J37: =J36/J12 -> 0.045568936 | K37: =K36/K12 -> 0.061273126 | L37: =L36/L12 -> 0.070129689 | M37: =M36/M12 -> 0.075745646 | N37: =N36/N12 -> 0.082375257 | ... Q37: =Q36/Q12 -> 0.087675912
A39: PRESENT VALUE OF FCFF
A40: Forecast year (t) | B40: # | G40: 1 | H40: 2 | I40: 3 | J40: 4 | K40: 5 | L40: 6 | M40: 7 | N40: 8 | O40: 9 | P40: 10
A41: Discount factor | B41: x | G41: =1/(1+Assumptions!$F$24)^G40 -> 0.89271951 | H41: =1/(1+Assumptions!$F$24)^H40 -> 0.79694813 | I41: =1/(1+Assumptions!$F$24)^I40 -> 0.71145115 | J41: =1/(1+Assumptions!$F$24)^J40 -> 0.63512632 | K41: =1/(1+Assumptions!$F$24)^K40 -> 0.56698966 | L41: =1/(1+Assumptions!$F$24)^L40 -> 0.50616273 | M41: =1/(1+Assumptions!$F$24)^M40 -> 0.45186135 | N41: =1/(1+Assumptions!$F$24)^N40 -> 0.40338544 | ... P41: =1/(1+Assumptions!$F$24)^P40 -> 0.32147727
A42: PV of FCFF | B42: ₹ Cr | G42: =G36*G41 -> -739.31102 | H42: =H36*H41 -> -90.654284 | I42: =I36*I41 -> 1522.8036 | J42: =J36*J41 -> 3399.2741 | K42: =K36*K41 -> 5509.4656 | L42: =L36*L41 -> 7348.444 | M42: =M36*M41 -> 8859.1254 | N42: =N36*N41 -> 10382.851 | ... P42: =P36*P41 -> 11340.965
A44: TERMINAL VALUE & EQUITY BRIDGE
A45: Sum of PV of explicit FCFF (FY26E–FY35E) | B45: ₹ Cr | F45: =SUM(G42:P42) -> 58699.654
A46: Terminal year FCFF (FY35E × (1+g)) | B46: ₹ Cr | F46: =P36*(1+Assumptions!F28) -> 37394.317
A47: Terminal Value (Gordon growth) | B47: ₹ Cr | F47: =F46/(Assumptions!F24-Assumptions!F28) -> 621450.19
A48: PV of Terminal Value | B48: ₹ Cr | F48: =F47/(1+Assumptions!F24)^Assumptions!F27 -> 199782.11
A49: Enterprise Value | B49: ₹ Cr | F49: =F45+F48 -> 258481.77
A50: Less: Total debt | B50: ₹ Cr | F50: =-Assumptions!F10 -> -2045
A51: Plus: Cash, bank balances & investments | B51: ₹ Cr | F51: =Assumptions!F11 -> 16806
A52: Equity Value | B52: ₹ Cr | F52: =F49+F50+F51 -> 273242.77
A53: Shares outstanding | B53: cr | F53: =Assumptions!F8 -> 951.5
A54: Implied per share value | B54: ₹ | F54: =F52/F53 -> 287.17054
A55: Current share price | B55: ₹ | F55: =Assumptions!F7 -> 251
A56: Implied upside / (downside) | B56: % | F56: =F54/F55-1 -> 0.14410573

Sheet Sensitivity
A1: Eternal Limited — DCF Sensitivity Analysis
A2: Two-way sensitivity tables for implied per share value (₹).
A3: Active case: | B3: =Assumptions!T7 -> Optimistic Case | D3: WACC: | E3: =Assumptions!F24 -> 0.12017267 | F3: Term g: | G3: =Assumptions!F28 -> 0.06 | H3: Implied / share: | I3: =DCF!F54 -> 287.17054
A5: ="Active case → "&Assumptions!T7&": WACC "&TEXT(Assumptions!F24,"0.00%")&", terminal g "&TEXT(Assumptions!F28,"0.00%")&" → ₹"&TEXT(DCF!F54,"0.00")&" / share (vs current ₹"&TEXT(DCF!F55,"0.00")&", upside "&TEXT(DCF!F56,"0.0%;(0.0%)")&")" -> Active case → Optimistic Case: WACC 12.02%, terminal g 6.00% → ₹287.17 / share (vs current ₹251.00, upside 14.4%)
A7: SENSITIVITY 1: Implied Per Share Value (₹) — WACC × Terminal Growth
A8: Terminal growth ↓ / WACC → | C8: 0.11 | D8: 0.115 | E8: 0.12 | F8: 0.13 | G8: 0.14 | H8: 0.15
B9: 0.03 | C9: {=(SUMPRODUCT(DCF!$G$36:$P$36/(1+C$8)^DCF!$G$40:$P$40)+DCF!$P$36*(1+$B9)/(C$8-$B9)/(1+C$8)^Assumptions!$F$27-Assumptions!$F$10+Assumptions!$F$11)/Assumptions!$F$8} -> 249.77679 | D9: {=(SUMPRODUCT(DCF!$G$36:$P$36/(1+D$8)^DCF!$G$40:$P$40)+DCF!$P$36*(1+$B9)/(D$8-$B9)/(1+D$8)^Assumptions!$F$27-Assumptions!$F$10+Assumptions!$F$11)/Assumptions!$F$8} -> 230.69753 | E9: {=(SUMPRODUCT(DCF!$G$36:$P$36/(1+E$8)^DCF!$G$40:$P$40)+DCF!$P$36*(1+$B9)/(E$8-$B9)/(1+E$8)^Assumptions!$F$27-Assumptions!$F$10+Assumptions!$F$11)/Assumptions!$F$8} -> 213.89492 | F9: {=(SUMPRODUCT(DCF!$G$36:$P$36/(1+F$8)^DCF!$G$40:$P$40)+DCF!$P$36*(1+$B9)/(F$8-$B9)/(1+F$8)^Assumptions!$F$27-Assumptions!$F$10+Assumptions!$F$11)/Assumptions!$F$8} -> 185.73249 | G9: {=(SUMPRODUCT(DCF!$G$36:$P$36/(1+G$8)^DCF!$G$40:$P$40)+DCF!$P$36*(1+$B9)/(G$8-$B9)/(1+G$8)^Assumptions!$F$27-Assumptions!$F$10+Assumptions!$F$11)/Assumptions!$F$8} -> 163.14775 | H9: {=(SUMPRODUCT(DCF!$G$36:$P$36/(1+H$8)^DCF!$G$40:$P$40)+DCF!$P$36*(1+$B9)/(H$8-$B9)/(1+H$8)^Assumptions!$F$27-Assumptions!$F$10+Assumptions!$F$11)/Assumptions!$F$8} -> 144.71572
B10: 0.04 | C10: {=(SUMPRODUCT(DCF!$G$36:$P$36/(1+C$8)^DCF!$G$40:$P$40)+DCF!$P$36*(1+$B10)/(C$8-$B10)/(1+C$8)^Assumptions!$F$27-Assumptions!$F$10+Assumptions!$F$11)/Assumptions!$F$8} -> 275.65869 | D10: {=(SUMPRODUCT(DCF!$G$36:$P$36/(1+D$8)^DCF!$G$40:$P$40)+DCF!$P$36*(1+$B10)/(D$8-$B10)/(1+D$8)^Assumptions!$F$27-Assumptions!$F$10+Assumptions!$F$11)/Assumptions!$F$8} -> 252.53172 | E10: {=(SUMPRODUCT(DCF!$G$36:$P$36/(1+E$8)^DCF!$G$40:$P$40)+DCF!$P$36*(1+$B10)/(E$8-$B10)/(1+E$8)^Assumptions!$F$27-Assumptions!$F$10+Assumptions!$F$11)/Assumptions!$F$8} -> 232.46426 | F10: {=(SUMPRODUCT(DCF!$G$36:$P$36/(1+F$8)^DCF!$G$40:$P$40)+DCF!$P$36*(1+$B10)/(F$8-$B10)/(1+F$8)^Assumptions!$F$27-Assumptions!$F$10+Assumptions!$F$11)/Assumptions!$F$8} -> 199.4458 | G10: {=(SUMPRODUCT(DCF!$G$36:$P$36/(1+G$8)^DCF!$G$40:$P$40)+DCF!$P$36*(1+$B10)/(G$8-$B10)/(1+G$8)^Assumptions!$F$27-Assumptions!$F$10+Assumptions!$F$11)/Assumptions!$F$8} -> 173.5124 | H10: {=(SUMPRODUCT(DCF!$G$36:$P$36/(1+H$8)^DCF!$G$40:$P$40)+DCF!$P$36*(1+$B10)/(H$8-$B10)/(1+H$8)^Assumptions!$F$27-Assumptions!$F$10+Assumptions!$F$11)/Assumptions!$F$8} -> 152.70001
B11: 0.05 | C11: {=(SUMPRODUCT(DCF!$G$36:$P$36/(1+C$8)^DCF!$G$40:$P$40)+DCF!$P$36*(1+$B11)/(C$8-$B11)/(1+C$8)^Assumptions!$F$27-Assumptions!$F$10+Assumptions!$F$11)/Assumptions!$F$8} -> 310.16789 | D11: {=(SUMPRODUCT(DCF!$G$36:$P$36/(1+D$8)^DCF!$G$40:$P$40)+DCF!$P$36*(1+$B11)/(D$8-$B11)/(1+D$8)^Assumptions!$F$27-Assumptions!$F$10+Assumptions!$F$11)/Assumptions!$F$8} -> 281.08411 | E11: {=(SUMPRODUCT(DCF!$G$36:$P$36/(1+E$8)^DCF!$G$40:$P$40)+DCF!$P$36*(1+$B11)/(E$8-$B11)/(1+E$8)^Assumptions!$F$27-Assumptions!$F$10+Assumptions!$F$11)/Assumptions!$F$8} -> 256.33911 | F11: {=(SUMPRODUCT(DCF!$G$36:$P$36/(1+F$8)^DCF!$G$40:$P$40)+DCF!$P$36*(1+$B11)/(F$8-$B11)/(1+F$8)^Assumptions!$F$27-Assumptions!$F$10+Assumptions!$F$11)/Assumptions!$F$8} -> 216.58745 | G11: {=(SUMPRODUCT(DCF!$G$36:$P$36/(1+G$8)^DCF!$G$40:$P$40)+DCF!$P$36*(1+$B11)/(G$8-$B11)/(1+G$8)^Assumptions!$F$27-Assumptions!$F$10+Assumptions!$F$11)/Assumptions!$F$8} -> 186.18031 | H11: {=(SUMPRODUCT(DCF!$G$36:$P$36/(1+H$8)^DCF!$G$40:$P$40)+DCF!$P$36*(1+$B11)/(H$8-$B11)/(1+H$8)^Assumptions!$F$27-Assumptions!$F$10+Assumptions!$F$11)/Assumptions!$F$8} -> 162.28117
B12: 0.06 | C12: {=(SUMPRODUCT(DCF!$G$36:$P$36/(1+C$8)^DCF!$G$40:$P$40)+DCF!$P$36*(1+$B12)/(C$8-$B12)/(1+C$8)^Assumptions!$F$27-Assumptions!$F$10+Assumptions!$F$11)/Assumptions!$F$8} -> 358.48076 | D12: {=(SUMPRODUCT(DCF!$G$36:$P$36/(1+D$8)^DCF!$G$40:$P$40)+DCF!$P$36*(1+$B12)/(D$8-$B12)/(1+D$8)^Assumptions!$F$27-Assumptions!$F$10+Assumptions!$F$11)/Assumptions!$F$8} -> 320.01919 | E12: {=(SUMPRODUCT(DCF!$G$36:$P$36/(1+E$8)^DCF!$G$40:$P$40)+DCF!$P$36*(1+$B12)/(E$8-$B12)/(1+E$8)^Assumptions!$F$27-Assumptions!$F$10+Assumptions!$F$11)/Assumptions!$F$8} -> 288.17225 | F12: {=(SUMPRODUCT(DCF!$G$36:$P$36/(1+F$8)^DCF!$G$40:$P$40)+DCF!$P$36*(1+$B12)/(F$8-$B12)/(1+F$8)^Assumptions!$F$27-Assumptions!$F$10+Assumptions!$F$11)/Assumptions!$F$8} -> 238.6267 | G12: {=(SUMPRODUCT(DCF!$G$36:$P$36/(1+G$8)^DCF!$G$40:$P$40)+DCF!$P$36*(1+$B12)/(G$8-$B12)/(1+G$8)^Assumptions!$F$27-Assumptions!$F$10+Assumptions!$F$11)/Assumptions!$F$8} -> 202.01519 | H12: {=(SUMPRODUCT(DCF!$G$36:$P$36/(1+H$8)^DCF!$G$40:$P$40)+DCF!$P$36*(1+$B12)/(H$8-$B12)/(1+H$8)^Assumptions!$F$27-Assumptions!$F$10+Assumptions!$F$11)/Assumptions!$F$8} -> 173.99146
B13: 0.07 | C13: {=(SUMPRODUCT(DCF!$G$36:$P$36/(1+C$8)^DCF!$G$40:$P$40)+DCF!$P$36*(1+$B13)/(C$8-$B13)/(1+C$8)^Assumptions!$F$27-Assumptions!$F$10+Assumptions!$F$11)/Assumptions!$F$8} -> 430.95008 | D13: {=(SUMPRODUCT(DCF!$G$36:$P$36/(1+D$8)^DCF!$G$40:$P$40)+DCF!$P$36*(1+$B13)/(D$8-$B13)/(1+D$8)^Assumptions!$F$27-Assumptions!$F$10+Assumptions!$F$11)/Assumptions!$F$8} -> 376.25876 | E13: {=(SUMPRODUCT(DCF!$G$36:$P$36/(1+E$8)^DCF!$G$40:$P$40)+DCF!$P$36*(1+$B13)/(E$8-$B13)/(1+E$8)^Assumptions!$F$27-Assumptions!$F$10+Assumptions!$F$11)/Assumptions!$F$8} -> 332.73864 | F13: {=(SUMPRODUCT(DCF!$G$36:$P$36/(1+F$8)^DCF!$G$40:$P$40)+DCF!$P$36*(1+$B13)/(F$8-$B13)/(1+F$8)^Assumptions!$F$27-Assumptions!$F$10+Assumptions!$F$11)/Assumptions!$F$8} -> 268.01238 | G13: {=(SUMPRODUCT(DCF!$G$36:$P$36/(1+G$8)^DCF!$G$40:$P$40)+DCF!$P$36*(1+$B13)/(G$8-$B13)/(1+G$8)^Assumptions!$F$27-Assumptions!$F$10+Assumptions!$F$11)/Assumptions!$F$8} -> 222.37432 | H13: {=(SUMPRODUCT(DCF!$G$36:$P$36/(1+H$8)^DCF!$G$40:$P$40)+DCF!$P$36*(1+$B13)/(H$8-$B13)/(1+H$8)^Assumptions!$F$27-Assumptions!$F$10+Assumptions!$F$11)/Assumptions!$F$8} -> 188.62933
A15: SENSITIVITY 2: Implied Per Share Value (₹) — WACC × Terminal Adj. EBITDA Margin
A16: Terminal margin ↓ / WACC → | C16: 0.11 | D16: 0.115 | E16: 0.12 | F16: 0.13 | G16: 0.14 | H16: 0.15
B17: 0.1 | C17: {=(SUMPRODUCT(DCF!$G$36:$P$36/(1+C$16)^DCF!$G$40:$P$40)+(DCF!$P$12*(1+Assumptions!$F$28)*(($B17-Assumptions!$Q$46-Assumptions!$Q$47)*(1-Assumptions!$Q$50)+Assumptions!$Q$47-Assumptions!$Q$48)-DCF!$P$12*Assumptions!$F$28*Assumptions!$Q$49)/(C$16-Assumptions!$F$28)/(1+C$16)^Assumptions!$F$27-Assumptions!$F$10+Assumptions!$F$11)/Assumptions!$F$8} -> 215.11576 | D17: {=(SUMPRODUCT(DCF!$G$36:$P$36/(1+D$16)^DCF!$G$40:$P$40)+(DCF!$P$12*(1+Assumptions!$F$28)*(($B17-Assumptions!$Q$46-Assumptions!$Q$47)*(1-Assumptions!$Q$50)+Assumptions!$Q$47-Assumptions!$Q$48)-DCF!$P$12*Assumptions!$F$28*Assumptions!$Q$49)/(D$16-Assumptions!$F$28)/(1+D$16)^Assumptions!$F$27-Assumptions!$F$10+Assumptions!$F$11)/Assumptions!$F$8} -> 195.41531 | E17: {=(SUMPRODUCT(DCF!$G$36:$P$36/(1+E$16)^DCF!$G$40:$P$40)+(DCF!$P$12*(1+Assumptions!$F$28)*(($B17-Assumptions!$Q$46-Assumptions!$Q$47)*(1-Assumptions!$Q$50)+Assumptions!$Q$47-Assumptions!$Q$48)-DCF!$P$12*Assumptions!$F$28*Assumptions!$Q$49)/(E$16-Assumptions!$F$28)/(1+E$16)^Assumptions!$F$27-Assumptions!$F$10+Assumptions!$F$11)/Assumptions!$F$8} -> 178.94991 | F17: {=(SUMPRODUCT(DCF!$G$36:$P$36/(1+F$16)^DCF!$G$40:$P$40)+(DCF!$P$12*(1+Assumptions!$F$28)*(($B17-Assumptions!$Q$46-Assumptions!$Q$47)*(1-Assumptions!$Q$50)+Assumptions!$Q$47-Assumptions!$Q$48)-DCF!$P$12*Assumptions!$F$28*Assumptions!$Q$49)/(F$16-Assumptions!$F$28)/(1+F$16)^Assumptions!$F$27-Assumptions!$F$10+Assumptions!$F$11)/Assumptions!$F$8} -> 152.97018 | G17: {=(SUMPRODUCT(DCF!$G$36:$P$36/(1+G$16)^DCF!$G$40:$P$40)+(DCF!$P$12*(1+Assumptions!$F$28)*(($B17-Assumptions!$Q$46-Assumptions!$Q$47)*(1-Assumptions!$Q$50)+Assumptions!$Q$47-Assumptions!$Q$48)-DCF!$P$12*Assumptions!$F$28*Assumptions!$Q$49)/(G$16-Assumptions!$F$28)/(1+G$16)^Assumptions!$F$27-Assumptions!$F$10+Assumptions!$F$11)/Assumptions!$F$8} -> 133.3867 | H17: {=(SUMPRODUCT(DCF!$G$36:$P$36/(1+H$16)^DCF!$G$40:$P$40)+(DCF!$P$12*(1+Assumptions!$F$28)*(($B17-Assumptions!$Q$46-Assumptions!$Q$47)*(1-Assumptions!$Q$50)+Assumptions!$Q$47-Assumptions!$Q$48)-DCF!$P$12*Assumptions!$F$28*Assumptions!$Q$49)/(H$16-Assumptions!$F$28)/(1+H$16)^Assumptions!$F$27-Assumptions!$F$10+Assumptions!$F$11)/Assumptions!$F$8} -> 118.09015
B18: 0.12 | C18: {=(SUMPRODUCT(DCF!$G$36:$P$36/(1+C$16)^DCF!$G$40:$P$40)+(DCF!$P$12*(1+Assumptions!$F$28)*(($B18-Assumptions!$Q$46-Assumptions!$Q$47)*(1-Assumptions!$Q$50)+Assumptions!$Q$47-Assumptions!$Q$48)-DCF!$P$12*Assumptions!$F$28*Assumptions!$Q$49)/(C$16-Assumptions!$F$28)/(1+C$16)^Assumptions!$F$27-Assumptions!$F$10+Assumptions!$F$11)/Assumptions!$F$8} -> 263.65909 | D18: {=(SUMPRODUCT(DCF!$G$36:$P$36/(1+D$16)^DCF!$G$40:$P$40)+(DCF!$P$12*(1+Assumptions!$F$28)*(($B18-Assumptions!$Q$46-Assumptions!$Q$47)*(1-Assumptions!$Q$50)+Assumptions!$Q$47-Assumptions!$Q$48)-DCF!$P$12*Assumptions!$F$28*Assumptions!$Q$49)/(D$16-Assumptions!$F$28)/(1+D$16)^Assumptions!$F$27-Assumptions!$F$10+Assumptions!$F$11)/Assumptions!$F$8} -> 237.60613 | E18: {=(SUMPRODUCT(DCF!$G$36:$P$36/(1+E$16)^DCF!$G$40:$P$40)+(DCF!$P$12*(1+Assumptions!$F$28)*(($B18-Assumptions!$Q$46-Assumptions!$Q$47)*(1-Assumptions!$Q$50)+Assumptions!$Q$47-Assumptions!$Q$48)-DCF!$P$12*Assumptions!$F$28*Assumptions!$Q$49)/(E$16-Assumptions!$F$28)/(1+E$16)^Assumptions!$F$27-Assumptions!$F$10+Assumptions!$F$11)/Assumptions!$F$8} -> 215.93255 | F18: {=(SUMPRODUCT(DCF!$G$36:$P$36/(1+F$16)^DCF!$G$40:$P$40)+(DCF!$P$12*(1+Assumptions!$F$28)*(($B18-Assumptions!$Q$46-Assumptions!$Q$47)*(1-Assumptions!$Q$50)+Assumptions!$Q$47-Assumptions!$Q$48)-DCF!$P$12*Assumptions!$F$28*Assumptions!$Q$49)/(F$16-Assumptions!$F$28)/(1+F$16)^Assumptions!$F$27-Assumptions!$F$10+Assumptions!$F$11)/Assumptions!$F$8} -> 181.97344 | G18: {=(SUMPRODUCT(DCF!$G$36:$P$36/(1+G$16)^DCF!$G$40:$P$40)+(DCF!$P$12*(1+Assumptions!$F$28)*(($B18-Assumptions!$Q$46-Assumptions!$Q$47)*(1-Assumptions!$Q$50)+Assumptions!$Q$47-Assumptions!$Q$48)-DCF!$P$12*Assumptions!$F$28*Assumptions!$Q$49)/(G$16-Assumptions!$F$28)/(1+G$16)^Assumptions!$F$27-Assumptions!$F$10+Assumptions!$F$11)/Assumptions!$F$8} -> 156.62427 | H18: {=(SUMPRODUCT(DCF!$G$36:$P$36/(1+H$16)^DCF!$G$40:$P$40)+(DCF!$P$12*(1+Assumptions!$F$28)*(($B18-Assumptions!$Q$46-Assumptions!$Q$47)*(1-Assumptions!$Q$50)+Assumptions!$Q$47-Assumptions!$Q$48)-DCF!$P$12*Assumptions!$F$28*Assumptions!$Q$49)/(H$16-Assumptions!$F$28)/(1+H$16)^Assumptions!$F$27-Assumptions!$F$10+Assumptions!$F$11)/Assumptions!$F$8} -> 137.01831
B19: 0.135 | C19: {=(SUMPRODUCT(DCF!$G$36:$P$36/(1+C$16)^DCF!$G$40:$P$40)+(DCF!$P$12*(1+Assumptions!$F$28)*(($B19-Assumptions!$Q$46-Assumptions!$Q$47)*(1-Assumptions!$Q$50)+Assumptions!$Q$47-Assumptions!$Q$48)-DCF!$P$12*Assumptions!$F$28*Assumptions!$Q$49)/(C$16-Assumptions!$F$28)/(1+C$16)^Assumptions!$F$27-Assumptions!$F$10+Assumptions!$F$11)/Assumptions!$F$8} -> 300.06658 | D19: {=(SUMPRODUCT(DCF!$G$36:$P$36/(1+D$16)^DCF!$G$40:$P$40)+(DCF!$P$12*(1+Assumptions!$F$28)*(($B19-Assumptions!$Q$46-Assumptions!$Q$47)*(1-Assumptions!$Q$50)+Assumptions!$Q$47-Assumptions!$Q$48)-DCF!$P$12*Assumptions!$F$28*Assumptions!$Q$49)/(D$16-Assumptions!$F$28)/(1+D$16)^Assumptions!$F$27-Assumptions!$F$10+Assumptions!$F$11)/Assumptions!$F$8} -> 269.24925 | E19: {=(SUMPRODUCT(DCF!$G$36:$P$36/(1+E$16)^DCF!$G$40:$P$40)+(DCF!$P$12*(1+Assumptions!$F$28)*(($B19-Assumptions!$Q$46-Assumptions!$Q$47)*(1-Assumptions!$Q$50)+Assumptions!$Q$47-Assumptions!$Q$48)-DCF!$P$12*Assumptions!$F$28*Assumptions!$Q$49)/(E$16-Assumptions!$F$28)/(1+E$16)^Assumptions!$F$27-Assumptions!$F$10+Assumptions!$F$11)/Assumptions!$F$8} -> 243.66952 | F19: {=(SUMPRODUCT(DCF!$G$36:$P$36/(1+F$16)^DCF!$G$40:$P$40)+(DCF!$P$12*(1+Assumptions!$F$28)*(($B19-Assumptions!$Q$46-Assumptions!$Q$47)*(1-Assumptions!$Q$50)+Assumptions!$Q$47-Assumptions!$Q$48)-DCF!$P$12*Assumptions!$F$28*Assumptions!$Q$49)/(F$16-Assumptions!$F$28)/(1+F$16)^Assumptions!$F$27-Assumptions!$F$10+Assumptions!$F$11)/Assumptions!$F$8} -> 203.72588 | G19: {=(SUMPRODUCT(DCF!$G$36:$P$36/(1+G$16)^DCF!$G$40:$P$40)+(DCF!$P$12*(1+Assumptions!$F$28)*(($B19-Assumptions!$Q$46-Assumptions!$Q$47)*(1-Assumptions!$Q$50)+Assumptions!$Q$47-Assumptions!$Q$48)-DCF!$P$12*Assumptions!$F$28*Assumptions!$Q$49)/(G$16-Assumptions!$F$28)/(1+G$16)^Assumptions!$F$27-Assumptions!$F$10+Assumptions!$F$11)/Assumptions!$F$8} -> 174.05246 | H19: {=(SUMPRODUCT(DCF!$G$36:$P$36/(1+H$16)^DCF!$G$40:$P$40)+(DCF!$P$12*(1+Assumptions!$F$28)*(($B19-Assumptions!$Q$46-Assumptions!$Q$47)*(1-Assumptions!$Q$50)+Assumptions!$Q$47-Assumptions!$Q$48)-DCF!$P$12*Assumptions!$F$28*Assumptions!$Q$49)/(H$16-Assumptions!$F$28)/(1+H$16)^Assumptions!$F$27-Assumptions!$F$10+Assumptions!$F$11)/Assumptions!$F$8} -> 151.21443
B20: 0.16 | C20: {=(SUMPRODUCT(DCF!$G$36:$P$36/(1+C$16)^DCF!$G$40:$P$40)+(DCF!$P$12*(1+Assumptions!$F$28)*(($B20-Assumptions!$Q$46-Assumptions!$Q$47)*(1-Assumptions!$Q$50)+Assumptions!$Q$47-Assumptions!$Q$48)-DCF!$P$12*Assumptions!$F$28*Assumptions!$Q$49)/(C$16-Assumptions!$F$28)/(1+C$16)^Assumptions!$F$27-Assumptions!$F$10+Assumptions!$F$11)/Assumptions!$F$8} -> 360.74574 | D20: {=(SUMPRODUCT(DCF!$G$36:$P$36/(1+D$16)^DCF!$G$40:$P$40)+(DCF!$P$12*(1+Assumptions!$F$28)*(($B20-Assumptions!$Q$46-Assumptions!$Q$47)*(1-Assumptions!$Q$50)+Assumptions!$Q$47-Assumptions!$Q$48)-DCF!$P$12*Assumptions!$F$28*Assumptions!$Q$49)/(D$16-Assumptions!$F$28)/(1+D$16)^Assumptions!$F$27-Assumptions!$F$10+Assumptions!$F$11)/Assumptions!$F$8} -> 321.98777 | E20: {=(SUMPRODUCT(DCF!$G$36:$P$36/(1+E$16)^DCF!$G$40:$P$40)+(DCF!$P$12*(1+Assumptions!$F$28)*(($B20-Assumptions!$Q$46-Assumptions!$Q$47)*(1-Assumptions!$Q$50)+Assumptions!$Q$47-Assumptions!$Q$48)-DCF!$P$12*Assumptions!$F$28*Assumptions!$Q$49)/(E$16-Assumptions!$F$28)/(1+E$16)^Assumptions!$F$27-Assumptions!$F$10+Assumptions!$F$11)/Assumptions!$F$8} -> 289.89781 | F20: {=(SUMPRODUCT(DCF!$G$36:$P$36/(1+F$16)^DCF!$G$40:$P$40)+(DCF!$P$12*(1+Assumptions!$F$28)*(($B20-Assumptions!$Q$46-Assumptions!$Q$47)*(1-Assumptions!$Q$50)+Assumptions!$Q$47-Assumptions!$Q$48)-DCF!$P$12*Assumptions!$F$28*Assumptions!$Q$49)/(F$16-Assumptions!$F$28)/(1+F$16)^Assumptions!$F$27-Assumptions!$F$10+Assumptions!$F$11)/Assumptions!$F$8} -> 239.97996 | G20: {=(SUMPRODUCT(DCF!$G$36:$P$36/(1+G$16)^DCF!$G$40:$P$40)+(DCF!$P$12*(1+Assumptions!$F$28)*(($B20-Assumptions!$Q$46-Assumptions!$Q$47)*(1-Assumptions!$Q$50)+Assumptions!$Q$47-Assumptions!$Q$48)-DCF!$P$12*Assumptions!$F$28*Assumptions!$Q$49)/(G$16-Assumptions!$F$28)/(1+G$16)^Assumptions!$F$27-Assumptions!$F$10+Assumptions!$F$11)/Assumptions!$F$8} -> 203.09943 | H20: {=(SUMPRODUCT(DCF!$G$36:$P$36/(1+H$16)^DCF!$G$40:$P$40)+(DCF!$P$12*(1+Assumptions!$F$28)*(($B20-Assumptions!$Q$46-Assumptions!$Q$47)*(1-Assumptions!$Q$50)+Assumptions!$Q$47-Assumptions!$Q$48)-DCF!$P$12*Assumptions!$F$28*Assumptions!$Q$49)/(H$16-Assumptions!$F$28)/(1+H$16)^Assumptions!$F$27-Assumptions!$F$10+Assumptions!$F$11)/Assumptions!$F$8} -> 174.87463
B21: 0.2 | C21: {=(SUMPRODUCT(DCF!$G$36:$P$36/(1+C$16)^DCF!$G$40:$P$40)+(DCF!$P$12*(1+Assumptions!$F$28)*(($B21-Assumptions!$Q$46-Assumptions!$Q$47)*(1-Assumptions!$Q$50)+Assumptions!$Q$47-Assumptions!$Q$48)-DCF!$P$12*Assumptions!$F$28*Assumptions!$Q$49)/(C$16-Assumptions!$F$28)/(1+C$16)^Assumptions!$F$27-Assumptions!$F$10+Assumptions!$F$11)/Assumptions!$F$8} -> 457.83239 | D21: {=(SUMPRODUCT(DCF!$G$36:$P$36/(1+D$16)^DCF!$G$40:$P$40)+(DCF!$P$12*(1+Assumptions!$F$28)*(($B21-Assumptions!$Q$46-Assumptions!$Q$47)*(1-Assumptions!$Q$50)+Assumptions!$Q$47-Assumptions!$Q$48)-DCF!$P$12*Assumptions!$F$28*Assumptions!$Q$49)/(D$16-Assumptions!$F$28)/(1+D$16)^Assumptions!$F$27-Assumptions!$F$10+Assumptions!$F$11)/Assumptions!$F$8} -> 406.36941 | E21: {=(SUMPRODUCT(DCF!$G$36:$P$36/(1+E$16)^DCF!$G$40:$P$40)+(DCF!$P$12*(1+Assumptions!$F$28)*(($B21-Assumptions!$Q$46-Assumptions!$Q$47)*(1-Assumptions!$Q$50)+Assumptions!$Q$47-Assumptions!$Q$48)-DCF!$P$12*Assumptions!$F$28*Assumptions!$Q$49)/(E$16-Assumptions!$F$28)/(1+E$16)^Assumptions!$F$27-Assumptions!$F$10+Assumptions!$F$11)/Assumptions!$F$8} -> 363.86308 | F21: {=(SUMPRODUCT(DCF!$G$36:$P$36/(1+F$16)^DCF!$G$40:$P$40)+(DCF!$P$12*(1+Assumptions!$F$28)*(($B21-Assumptions!$Q$46-Assumptions!$Q$47)*(1-Assumptions!$Q$50)+Assumptions!$Q$47-Assumptions!$Q$48)-DCF!$P$12*Assumptions!$F$28*Assumptions!$Q$49)/(F$16-Assumptions!$F$28)/(1+F$16)^Assumptions!$F$27-Assumptions!$F$10+Assumptions!$F$11)/Assumptions!$F$8} -> 297.98648 | G21: {=(SUMPRODUCT(DCF!$G$36:$P$36/(1+G$16)^DCF!$G$40:$P$40)+(DCF!$P$12*(1+Assumptions!$F$28)*(($B21-Assumptions!$Q$46-Assumptions!$Q$47)*(1-Assumptions!$Q$50)+Assumptions!$Q$47-Assumptions!$Q$48)-DCF!$P$12*Assumptions!$F$28*Assumptions!$Q$49)/(G$16-Assumptions!$F$28)/(1+G$16)^Assumptions!$F$27-Assumptions!$F$10+Assumptions!$F$11)/Assumptions!$F$8} -> 249.57458 | H21: {=(SUMPRODUCT(DCF!$G$36:$P$36/(1+H$16)^DCF!$G$40:$P$40)+(DCF!$P$12*(1+Assumptions!$F$28)*(($B21-Assumptions!$Q$46-Assumptions!$Q$47)*(1-Assumptions!$Q$50)+Assumptions!$Q$47-Assumptions!$Q$48)-DCF!$P$12*Assumptions!$F$28*Assumptions!$Q$49)/(H$16-Assumptions!$F$28)/(1+H$16)^Assumptions!$F$27-Assumptions!$F$10+Assumptions!$F$11)/Assumptions!$F$8} -> 212.73095
A23: INTERPRETATION
A24: • Current market price of ₹251 implies long-run EBITDA margin >18% AND/OR terminal growth >7%, OR a lower WACC than modelled.
A25: • Base case (WACC 13.02%, g 5.00%, term margin 13.4%) implies ₹88/share — significantly below market.
A26: • Use Assumptions!F15:F17 to flex WACC inputs; G32:Q43 to flex segment growth and margin paths.

Sheet Balance Sheet
A1: Eternal Limited (formerly Zomato Limited) — Consolidated Balance Sheet
A2: As at March 31 of each fiscal year. All values in INR crores (1 crore = 10 million).
A4: Particulars | B4: ₹ Cr | C4: FY22 | D4: FY23 | E4: FY24 | F4: FY25
A5: ASSETS
A6: Non-current assets
A7: Property, plant and equipment | B7: ₹ Cr | C7: 50.9 | D7: 208.5 | E7: 287 | F7: 965
A8: Capital work-in-progress | B8: ₹ Cr | C8: 0.6 | D8: 7.5 | E8: 18 | F8: 51
A9: Right-of-use assets | B9: ₹ Cr | C9: 64.2 | D9: 427.2 | E9: 690 | F9: 1918
A10: Goodwill | B10: ₹ Cr | C10: 1209.3 | D10: 4716.6 | E10: 4717 | F10: 5737
A11: Other intangible assets | B11: ₹ Cr | C11: 79.9 | D11: 990.5 | E11: 754 | F11: 912
A12: Intangible assets under development | B12: ₹ Cr | C12: 0
A13: Investments (non-current) | B13: ₹ Cr | C13: 3086 | D13: 2279.6 | E13: 10365 | F13: 10920
A14: Other financial assets (non-current) | B14: ₹ Cr | C14: 5219.1 | D14: 1894.2 | E14: 747 | F14: 2744
A15: Tax assets (net) | B15: ₹ Cr | C15: 67 | D15: 116.1 | E15: 221 | F15: 129
A16: Other non-current assets | B16: ₹ Cr | C16: 5 | D16: 127.5 | E16: 99 | F16: 546
A17: Total non-current assets | B17: ₹ Cr | C17: 9782 | D17: 10767.7 | E17: 17898 | F17: 23922
A18: Current assets
A19: Inventories | B19: ₹ Cr | C19: 39.7 | D19: 82.7 | E19: 88 | F19: 176
A20: Investments (current) | B20: ₹ Cr | C20: 1631.7 | D20: 4485 | E20: 1280 | F20: 2272
A21: Trade receivables | B21: ₹ Cr | C21: 159.9 | D21: 456.9 | E21: 794 | F21: 1946
A22: Cash and cash equivalents | B22: ₹ Cr | C22: 392.3 | D22: 218.1 | E22: 309 | F22: 666
A23: Bank balances other than cash and cash equivalents | B23: ₹ Cr | C23: 1183.2 | D23: 798.7 | E23: 422 | F23: 2948
A24: Loans (current) | B24: ₹ Cr | C24: 375 | D24: 0.4 | E24: 0
A25: Other financial assets (current) | B25: ₹ Cr | C25: 3667.4 | D25: 4417.7 | E25: 2324 | F25: 2769
A26: Other current assets | B26: ₹ Cr | C26: 95.8 | D26: 371.5 | E26: 241 | F26: 924
A27: Total current assets | B27: ₹ Cr | C27: 7545 | D27: 10831 | E27: 5458 | F27: 11701
A28: Total assets | B28: ₹ Cr | C28: 17327 | D28: 21598.7 | E28: 23356 | F28: 35623
A29: EQUITY AND LIABILITIES
A30: Equity
A31: Equity share capital | B31: ₹ Cr | C31: 764.3 | D31: 836.4 | E31: 868 | F31: 907
A32: Other equity | B32: ₹ Cr | C32: 15741.2 | D32: 18623.4 | E32: 19545 | F32: 29410
A33: Equity attributable to owners of the Parent | B33: ₹ Cr | C33: 16505.5 | D33: 19459.8 | E33: 20413 | F33: 30317
A34: Non-controlling interests | B34: ₹ Cr | C34: -6.6 | D34: -6.6 | E34: -7 | F34: -7
A35: Total equity | B35: ₹ Cr | C35: 16498.9 | D35: 19453.2 | E35: 20406 | F35: 30310
A36: Liabilities
A37: Non-current liabilities
A38: Borrowings (non-current) | B38: ₹ Cr | C38: 0 | D38: 5.8 | E38: 0 | F38: 0
A39: Lease liabilities (non-current) | B39: ₹ Cr | C39: 51 | D39: 350.8 | E39: 588 | F39: 1654
A40: Other financial liabilities (non-current) | B40: ₹ Cr | C40: 0 | D40: 4.8 | E40: 3 | F40: 1
A41: Provisions (non-current) | B41: ₹ Cr | C41: 65.3 | D41: 93.6 | E41: 88 | F41: 120
A42: Deferred tax liabilities | B42: ₹ Cr | C42: 0 | D42: 249.5 | E42: 188 | F42: 212
A43: Other non-current liabilities | B43: ₹ Cr | C43: 0.3 | D43: 0
A44: Total non-current liabilities | B44: ₹ Cr | C44: 116.6 | D44: 704.5 | E44: 867 | F44: 1987
A45: Current liabilities
A46: Borrowings (current) | B46: ₹ Cr | C46: 0 | D46: 34.6 | E46: 0 | F46: 0
A47: Lease liabilities (current) | B47: ₹ Cr | C47: 19.3 | D47: 115.4 | E47: 161 | F47: 391
A48: Trade payables - micro & small enterprises | B48: ₹ Cr | C48: 6.7 | D48: 9.1 | E48: 15 | F48: 75
A49: Trade payables - others | B49: ₹ Cr | C49: 422.1 | D49: 670.7 | E49: 871 | F49: 1461
A50: Other financial liabilities (current) | B50: ₹ Cr | C50: 28.7 | D50: 309.6 | E50: 644 | F50: 913
A51: Other current liabilities | B51: ₹ Cr | C51: 216.2 | D51: 275.7 | E51: 363 | F51: 452
A52: Provisions (current) | B52: ₹ Cr | C52: 18.5 | D52: 25.9 | E52: 29 | F52: 34
A53: Total current liabilities | B53: ₹ Cr | C53: 711.5 | D53: 1441 | E53: 2083 | F53: 3326
A54: Total liabilities | B54: ₹ Cr | C54: 828.1 | D54: 2145.5 | E54: 2950 | F54: 2950
A55: Total equity and liabilities | B55: ₹ Cr | C55: 17327 | D55: 21598.7 | E55: 23356 | F55: 35623

Sheet P&L
A1: Eternal Limited (formerly Zomato Limited) — Consolidated Statement of Profit and Loss
A2: For the year ended March 31. All values in INR crores (1 crore = 10 million).
A4: Particulars | B4: ₹ Cr | C4: FY22 | D4: FY23 | E4: FY24 | F4: FY25
A5: INCOME
A6: Revenue from operations | B6: ₹ Cr | C6: 4192.4 | D6: 7079.4 | E6: 12114 | F6: 20243
A7: Other income | B7: ₹ Cr | C7: 494.9 | D7: 681.5 | E7: 847 | F7: 1077
A8: Total income (I) | B8: ₹ Cr | C8: 4687.3 | D8: 7760.9 | E8: 12961 | F8: 21320
A9: EXPENSES
A10: Purchase of stock-in-trade | B10: ₹ Cr | C10: 552.4 | D10: 1438.2 | E10: 2887 | F10: 5653
A11: Changes in inventories of stock-in-trade | B11: ₹ Cr | C11: -27.8 | D11: -43 | E11: -5 | F11: -88
A12: Employee benefits expense | B12: ₹ Cr | C12: 1633.1 | D12: 1465 | E12: 1659 | F12: 2558
A13: Finance costs | B13: ₹ Cr | C13: 12 | D13: 48.7 | E13: 72 | F13: 154
A14: Depreciation and amortisation expense | B14: ₹ Cr | C14: 150.3 | D14: 436.9 | E14: 526 | F14: 863
A15: Other expenses | B15: ₹ Cr | C15: 3885.5 | D15: 5429.5 | E15: 7531 | F15: 11483
A16: Total expenses (II) | B16: ₹ Cr | C16: 6205.5 | D16: 8775.3 | E16: 12670 | F16: 20623
A17: Profit / (loss) before share of P/(L) of associate, exceptional items and tax (III=I-II) | B17: ₹ Cr | C17: -1518.2 | D17: -1014.4 | E17: 291 | F17: 697
A18: Share of profit / (loss) of an associate and joint venture (IV) | B18: ₹ Cr | C18: 0.3 | D18: -0.3 | E18: 0 | F18: 0
A19: Profit / (loss) before exceptional items and tax (V=III+IV) | B19: ₹ Cr | C19: -1517.9 | D19: -1014.7 | E19: 291 | F19: 697
A20: Exceptional items (VI) | B20: ₹ Cr | C20: 297.4 | D20: 0.1 | E20: 0 | F20: 0
A21: Profit / (loss) before tax (VII=V-VI) | B21: ₹ Cr | C21: -1220.5 | D21: -1014.6 | E21: 291 | F21: 697
A22: Tax expense:
A23: Current tax | B23: ₹ Cr | C23: 2 | D23: 0.4 | E23: 1 | F23: 231
A24: Deferred tax | B24: ₹ Cr | C24: 0 | D24: -44 | E24: -61 | F24: -61
A25: Total tax expense (VIII) | B25: ₹ Cr | C25: 2 | D25: -43.6 | E25: -60 | F25: 170
A26: Profit / (loss) for the year (IX=VII-VIII) | B26: ₹ Cr | C26: -1222.5 | D26: -971 | E26: 351 | F26: 527
A27: Other comprehensive income / (loss) for the year (XII) | B27: ₹ Cr | C27: 2.2 | D27: -98.5 | E27: 55 | F27: 128
A28: Total comprehensive income / (loss) for the year (XIII=IX+XII) | B28: ₹ Cr | C28: -1220.3 | D28: -1069.5 | E28: 406 | F28: 655
A29: Profit / (loss) attributable to:
A30: Owners of the Parent | B30: ₹ Cr | C30: -1208.7 | D30: -971.3 | E30: 351 | F30: 527
A31: Non-controlling interest | B31: ₹ Cr | C31: -13.8 | D31: 0.3 | E31: 0 | F31: 0
A32: Earnings / (loss) per equity share (face value INR 1)
A33: Basic (INR) | B33: ₹ | C33: -1.67 | D33: -1.2 | E33: 0.41 | F33: 0.6
A34: Diluted (INR) | B34: ₹ | C34: -1.67 | D34: -1.2 | E34: 0.4 | F34: 0.58

Sheet Cash Flow
A1: Eternal Limited (formerly Zomato Limited) — Consolidated Statement of Cash Flows
A2: For the year ended March 31. All values in INR crores (1 crore = 10 million).
A4: Particulars | B4: ₹ Cr | C4: FY22 | D4: FY23 | E4: FY24 | F4: FY25
A5: A) CASH FLOWS FROM OPERATING ACTIVITIES
A6: Profit / (loss) before tax | B6: ₹ Cr | C6: -1220.5 | D6: -1014.6 | E6: 291 | F6: 697
A7: Adjustments for non-cash items (net) | B7: ₹ Cr | C7: 298.4 | D7: 377.3 | E7: 342 | F7: 822
A8: Operating profit / (loss) before working capital changes | B8: ₹ Cr | C8: -922.1 | D8: -637.3 | E8: 633 | F8: 1519
A9: Movements in working capital (net) | B9: ₹ Cr | C9: 248.3 | D9: -175.9 | E9: 118 | F9: -1093
A10: Cash generated from / (used in) operations | B10: ₹ Cr | C10: -673.8 | D10: -813.2 | E10: 751 | F10: 426
A11: Income taxes (paid) / refund (net) | B11: ₹ Cr | C11: -19.2 | D11: -30.8 | E11: -105 | F11: -118
A12: Net cash from / (used in) operating activities (A) | B12: ₹ Cr | C12: -693 | D12: -844 | E12: 646 | F12: 308
A13: B) CASH FLOWS FROM INVESTING ACTIVITIES
A14: Purchase of property, plant and equipment (incl. CWIP, capital advances) | B14: ₹ Cr | C14: -59 | D14: -103 | E14: -215 | F14: -936
A15: Proceeds from sale of property, plant and equipment | B15: ₹ Cr | C15: 1.8 | D15: 1.6 | E15: 13 | F15: 5
A16: Net (investments in) / proceeds from bank deposits (>3 months) | B16: ₹ Cr | C16: -5530.8 | D16: 3288.6 | E16: 3994 | F16: -4755
A17: Net (investments in) / proceeds from mutual funds | B17: ₹ Cr | C17: 632.1 | D17: -1794 | E17: 2499 | F17: -588
A18: Net (investments in) / proceeds from government securities | B18: ₹ Cr | C18: -468.1 | D18: -565.2 | E18: -1485 | F18: -583
A19: Net (investments in) / proceeds from debentures and bonds | B19: ₹ Cr | C19: 0 | D19: -50 | E19: -5772 | F19: 50
A20: share-based payment on cancellation / cash settlement of options | B20: ₹ Cr | C20: -2627.8 | D20: -60.7 | E20: 1 | F20: -2005
A21: Loans given / (received back) | B21: ₹ Cr | C21: -375 | D21: -750.4 | E21: 0 | F21: 0
A22: Interest received | B22: ₹ Cr | C22: 112.6 | D22: 490.4 | E22: 618 | F22: 819
A23: Net cash from / (used in) investing activities (B) | B23: ₹ Cr | C23: -7937.8 | D23: 457.3 | E23: -347 | F23: -7993
A24: C) CASH FLOWS FROM FINANCING ACTIVITIES
A25: Proceeds from issue of equity shares (incl. CCCPS in FY22) | B25: ₹ Cr | C25: 9000 | D25: 4 | E25: 23 | F25: 8501
A26: Transaction costs paid on issue of shares | B26: ₹ Cr | C26: -225.7 | D26: 0 | E26: -1 | F26: -54
A27: Borrowings taken / (repaid) (net) | B27: ₹ Cr | C27: -1.3 | D27: -23.1 | E27: -40 | F27: 0
A28: Share-based payment on cancellation / cash settlement of options | B28: ₹ Cr | C28: -0.6 | D28: -0.2 | E28: 0 | F28: 0
A29: ESOP trust collections (net of tax) | B29: ₹ Cr | C29: 7.9 | D29: 6.7 | E29: 9 | F29: 4
A30: Payment of principal portion of lease liabilities | B30: ₹ Cr | C30: -20.3 | D30: -65.3 | E30: -129 | F30: -258
A31: Payment of interest portion of lease liabilities | B31: ₹ Cr | C31: -9.5 | D31: -40.2 | E31: -67 | F31: -147
A32: Other interest paid | B32: ₹ Cr | C32: -0.7 | D32: -9.3 | E32: -2 | F32: -4
A33: Net cash from / (used in) financing activities (C) | B33: ₹ Cr | C33: 8749.8 | D33: -127.4 | E33: -207 | F33: 8042
A34: NET CHANGE IN CASH AND CASH EQUIVALENTS
A35: Net increase / (decrease) in cash and cash equivalents (A+B+C) | B35: ₹ Cr | C35: 119 | D35: -514.1 | E35: 92 | F35: 357
A36: Cash acquired through business combination / (transferred on disposal) | B36: ₹ Cr | C36: -5.5 | D36: 339 | E36: 0 | F36: 0
A37: Net foreign exchange difference (incl. hyperinflation impact) | B37: ₹ Cr | C37: -27.7 | D37: 0.9 | E37: -1 | F37: 0
A38: Cash and cash equivalents at beginning of the year | B38: ₹ Cr | C38: 306.5 | D38: 392.3 | E38: 218 | F38: 309
A39: Cash and cash equivalents at end of the year | B39: ₹ Cr | C39: 392.3 | D39: 218.1 | E39: 309 | F39: 666

Sheet Equity
A1: Eternal Limited (formerly Zomato Limited) — Consolidated Statement of Changes in Equity
A2: Closing balances as at March 31. All values in INR crores (1 crore = 10 million).
A4: Particulars | B4: ₹ Cr | C4: FY22 | D4: FY23 | E4: FY24 | F4: FY25
A5: EQUITY SHARE CAPITAL
A6: Share capital — issued (gross) | B6: ₹ Cr | C6: 787.2 | D6: 855.4 | E6: 882 | F6: 965
A7: Less: Held by ESOP Trust (treasury shares) | B7: ₹ Cr | C7: -22.9 | D7: -19 | E7: -14 | F7: -58
A8: Equity share capital outstanding | B8: ₹ Cr | C8: 764.3 | D8: 836.4 | E8: 868 | F8: 907
A9: OTHER EQUITY — by component
A10: Capital reserve | B10: ₹ Cr | C10: 2.6 | D10: 2.6 | E10: 3 | F10: 3
A11: Share-based payment reserve | B11: ₹ Cr | C11: 1125.3 | D11: 1293.6 | E11: 683 | F11: 1253
A12: Securities premium | B12: ₹ Cr | C12: 21291.9 | D12: 24712.9 | E12: 24709 | F12: 33116
A13: Retained earnings | B13: ₹ Cr | C13: -6728.6 | D13: -7508.9 | E13: -6024 | F13: -5265
A14: Treasury shares (held by ESOP Trust) | B14: ₹ Cr | C14: 22.9 | D14: 19 | E14: 14 | F14: 15
A15: Equity instruments through OCI | B15: ₹ Cr | C15: 9.6 | D15: 73.6 | E15: 134 | F15: 181
A16: Debt instruments through OCI | B16: ₹ Cr | C16: 0 | D16: 0.1 | E16: -8 | F16: 81
A17: Foreign currency translation reserve | B17: ₹ Cr | C17: 17.5 | D17: 30.5 | E17: 37 | F17: 39
A18: Remeasurements of the defined benefit plans | B18: ₹ Cr | C18: 0 | D18: 0 | E18: -3 | F18: -13
A19: Total other equity | B19: ₹ Cr | C19: 15741.2 | D19: 18623.4 | E19: 19545 | F19: 29410
A20: EQUITY ATTRIBUTABLE TO OWNERS OF THE PARENT | B20: ₹ Cr | C20: 16505.5 | D20: 19459.8 | E20: 20413 | F20: 30317
A21: Non-controlling interests | B21: ₹ Cr | C21: -6.6 | D21: -6.6 | E21: -7 | F21: -7
A22: TOTAL EQUITY | B22: ₹ Cr | C22: 16498.9 | D22: 19453.2 | E22: 20406 | F22: 30310
A24: ROLL-FORWARD SUMMARY (Total equity)
A25: Opening balance | B25: ₹ Cr | C25: 7711.3 | D25: 16498.9 | E25: 19453.2 | F25: 20413
A26: Profit / (loss) for the year | B26: ₹ Cr | C26: -1222.5 | D26: -971 | E26: 351 | F26: 527
A27: Other comprehensive income / (loss) | B27: ₹ Cr | C27: 2.2 | D27: -98.5 | E27: 55 | F27: 128
A28: Issue of equity shares (net of transaction costs) | B28: ₹ Cr | C28: 8723.5 | D28: 4 | E28: 23 | F28: 8501
A29: Share-based payment expense (incl. ESOP movements) | B29: ₹ Cr | C29: 877.9 | D29: 506.5 | E29: -515 | F29: 798
A30: Other movements (NCI changes, transaction costs, bonus issue) | B30: ₹ Cr | C30: 406.5 | D30: 3513.3 | E30: 1052 | F30: -57
A31: Closing balance | B31: ₹ Cr | C31: 16498.9 | D31: 19453.2 | E31: 20406 | F31: 30310

Sheet PB_CACHE_JS

Sheet __tracelight_scratchpad__

Sheet _PB_CACHE_JS

Sheet ___tracelight_scratchpad__
